{
"meta":{"test_sets":[],"test_metrics":[],"learn_metrics":[{"best_value":"Min","name":"Logloss"}],"launch_mode":"Train","parameters":"","iteration_count":1000,"learn_sets":["learn"],"name":"experiment"},
"iterations":[
{"learn":[0.6876836194],"iteration":0,"passed_time":0.005377921472,"remaining_time":5.37254355},
{"learn":[0.6826714609],"iteration":1,"passed_time":0.01041252286,"remaining_time":5.195848909},
{"learn":[0.6787907999],"iteration":2,"passed_time":0.01532406057,"remaining_time":5.092696129},
{"learn":[0.6742086135],"iteration":3,"passed_time":0.02040132408,"remaining_time":5.079929696},
{"learn":[0.6702921162],"iteration":4,"passed_time":0.02530020788,"remaining_time":5.034741368},
{"learn":[0.6665627634],"iteration":5,"passed_time":0.03090559818,"remaining_time":5.120027433},
{"learn":[0.6631953339],"iteration":6,"passed_time":0.0362399295,"remaining_time":5.140892856},
{"learn":[0.6599263866],"iteration":7,"passed_time":0.04137046464,"remaining_time":5.129937615},
{"learn":[0.6570385451],"iteration":8,"passed_time":0.04638213807,"remaining_time":5.107188758},
{"learn":[0.6536077323],"iteration":9,"passed_time":0.05126704245,"remaining_time":5.075437202},
{"learn":[0.6509198353],"iteration":10,"passed_time":0.05614845017,"remaining_time":5.04825611},
{"learn":[0.6481029254],"iteration":11,"passed_time":0.06162068155,"remaining_time":5.073436114},
{"learn":[0.6449564501],"iteration":12,"passed_time":0.06709087758,"remaining_time":5.093745859},
{"learn":[0.6423256272],"iteration":13,"passed_time":0.07217868134,"remaining_time":5.083441414},
{"learn":[0.639027144],"iteration":14,"passed_time":0.07718876578,"remaining_time":5.068728953},
{"learn":[0.6360221841],"iteration":15,"passed_time":0.08202761505,"remaining_time":5.044698325},
{"learn":[0.633507964],"iteration":16,"passed_time":0.08707745844,"remaining_time":5.035125979},
{"learn":[0.631152142],"iteration":17,"passed_time":0.09256260494,"remaining_time":5.049804336},
{"learn":[0.629273567],"iteration":18,"passed_time":0.09839450344,"remaining_time":5.080263572},
{"learn":[0.6269117249],"iteration":19,"passed_time":0.1041921383,"remaining_time":5.105414779},
{"learn":[0.6249457159],"iteration":20,"passed_time":0.1100558907,"remaining_time":5.13070081},
{"learn":[0.6228703689],"iteration":21,"passed_time":0.115537565,"remaining_time":5.136169935},
{"learn":[0.6201395163],"iteration":22,"passed_time":0.1208396717,"remaining_time":5.133059097},
{"learn":[0.6179615049],"iteration":23,"passed_time":0.1260688808,"remaining_time":5.126801151},
{"learn":[0.6161202691],"iteration":24,"passed_time":0.131365211,"remaining_time":5.123243228},
{"learn":[0.6140208881],"iteration":25,"passed_time":0.136694267,"remaining_time":5.120777539},
{"learn":[0.6126198095],"iteration":26,"passed_time":0.1418660056,"remaining_time":5.112430498},
{"learn":[0.6110777031],"iteration":27,"passed_time":0.1472042261,"remaining_time":5.110089563},
{"learn":[0.6094654918],"iteration":28,"passed_time":0.1526524421,"remaining_time":5.111224872},
{"learn":[0.6074182073],"iteration":29,"passed_time":0.1584366286,"remaining_time":5.122784325},
{"learn":[0.6060227926],"iteration":30,"passed_time":0.1643344015,"remaining_time":5.136775324},
{"learn":[0.6042824543],"iteration":31,"passed_time":0.1700503686,"remaining_time":5.144023651},
{"learn":[0.601898468],"iteration":32,"passed_time":0.175430167,"remaining_time":5.140635499},
{"learn":[0.6007301625],"iteration":33,"passed_time":0.1808142986,"remaining_time":5.137253308},
{"learn":[0.5986632497],"iteration":34,"passed_time":0.1864042201,"remaining_time":5.139430641},
{"learn":[0.5963534979],"iteration":35,"passed_time":0.1921015495,"remaining_time":5.144052604},
{"learn":[0.5946697234],"iteration":36,"passed_time":0.1974865214,"remaining_time":5.139987029},
{"learn":[0.5931667183],"iteration":37,"passed_time":0.2028972202,"remaining_time":5.136503312},
{"learn":[0.5915008875],"iteration":38,"passed_time":0.2082533061,"remaining_time":5.131575056},
{"learn":[0.5902628248],"iteration":39,"passed_time":0.2137280903,"remaining_time":5.129474167},
{"learn":[0.5890084718],"iteration":40,"passed_time":0.2198258037,"remaining_time":5.141779164},
{"learn":[0.588044321],"iteration":41,"passed_time":0.2254282881,"remaining_time":5.141911905},
{"learn":[0.5859400532],"iteration":42,"passed_time":0.2308789655,"remaining_time":5.138399301},
{"learn":[0.584660257],"iteration":43,"passed_time":0.2363003689,"remaining_time":5.13416256},
{"learn":[0.5831222084],"iteration":44,"passed_time":0.2415455348,"remaining_time":5.126133016},
{"learn":[0.5813639403],"iteration":45,"passed_time":0.246842583,"remaining_time":5.119300525},
{"learn":[0.5792775267],"iteration":46,"passed_time":0.2528572882,"remaining_time":5.127085013},
{"learn":[0.5777375023],"iteration":47,"passed_time":0.2591531815,"remaining_time":5.139871434},
{"learn":[0.5768255141],"iteration":48,"passed_time":0.2649428946,"remaining_time":5.142054955},
{"learn":[0.5753176963],"iteration":49,"passed_time":0.2703745151,"remaining_time":5.137115786},
{"learn":[0.5738018208],"iteration":50,"passed_time":0.276200203,"remaining_time":5.139490051},
{"learn":[0.5728176385],"iteration":51,"passed_time":0.2821214036,"remaining_time":5.143290204},
{"learn":[0.5715624307],"iteration":52,"passed_time":0.2888880651,"remaining_time":5.161830145},
{"learn":[0.5706216831],"iteration":53,"passed_time":0.2955919868,"remaining_time":5.178333695},
{"learn":[0.5695868954],"iteration":54,"passed_time":0.3012003649,"remaining_time":5.175169907},
{"learn":[0.5680251091],"iteration":55,"passed_time":0.3072795479,"remaining_time":5.179855236},
{"learn":[0.5662321646],"iteration":56,"passed_time":0.3134881247,"remaining_time":5.186303537},
{"learn":[0.565716045],"iteration":57,"passed_time":0.3201959726,"remaining_time":5.200424245},
{"learn":[0.5646293958],"iteration":58,"passed_time":0.3267196391,"remaining_time":5.210901362},
{"learn":[0.5629506948],"iteration":59,"passed_time":0.3327852876,"remaining_time":5.213636173},
{"learn":[0.5618074347],"iteration":60,"passed_time":0.3385104677,"remaining_time":5.210841461},
{"learn":[0.5608617109],"iteration":61,"passed_time":0.3444728093,"remaining_time":5.211540245},
{"learn":[0.559598154],"iteration":62,"passed_time":0.3511253168,"remaining_time":5.22229241},
{"learn":[0.5584178603],"iteration":63,"passed_time":0.3574568835,"remaining_time":5.227806921},
{"learn":[0.5567301814],"iteration":64,"passed_time":0.3638183719,"remaining_time":5.23338735},
{"learn":[0.5559492566],"iteration":65,"passed_time":0.3705648231,"remaining_time":5.244053708},
{"learn":[0.5544544427],"iteration":66,"passed_time":0.3769475744,"remaining_time":5.249135626},
{"learn":[0.5532069248],"iteration":67,"passed_time":0.3841955697,"remaining_time":5.265739279},
{"learn":[0.5523273977],"iteration":68,"passed_time":0.3911572265,"remaining_time":5.277788085},
{"learn":[0.551029773],"iteration":69,"passed_time":0.3972745858,"remaining_time":5.27807664},
{"learn":[0.5501856817],"iteration":70,"passed_time":0.4032020989,"remaining_time":5.275700702},
{"learn":[0.5489217503],"iteration":71,"passed_time":0.4096922106,"remaining_time":5.280477381},
{"learn":[0.548209415],"iteration":72,"passed_time":0.4161195372,"remaining_time":5.284148096},
{"learn":[0.5474737772],"iteration":73,"passed_time":0.4225169185,"remaining_time":5.287171169},
{"learn":[0.5459635925],"iteration":74,"passed_time":0.4284188753,"remaining_time":5.283832795},
{"learn":[0.5448547945],"iteration":75,"passed_time":0.4342790042,"remaining_time":5.27991842},
{"learn":[0.5440493252],"iteration":76,"passed_time":0.4401525051,"remaining_time":5.276113795},
{"learn":[0.542688669],"iteration":77,"passed_time":0.4466219854,"remaining_time":5.279300904},
{"learn":[0.5417033403],"iteration":78,"passed_time":0.4528203103,"remaining_time":5.279082352},
{"learn":[0.5406979037],"iteration":79,"passed_time":0.4583595415,"remaining_time":5.271134727},
{"learn":[0.5386448223],"iteration":80,"passed_time":0.4641215384,"remaining_time":5.265773997},
{"learn":[0.5374150466],"iteration":81,"passed_time":0.4700934461,"remaining_time":5.262753457},
{"learn":[0.5359772801],"iteration":82,"passed_time":0.4762035182,"remaining_time":5.261188268},
{"learn":[0.5352891914],"iteration":83,"passed_time":0.4825863533,"remaining_time":5.262489282},
{"learn":[0.5338015999],"iteration":84,"passed_time":0.4881370474,"remaining_time":5.254651745},
{"learn":[0.5328899004],"iteration":85,"passed_time":0.4936591515,"remaining_time":5.24656354},
{"learn":[0.5315466366],"iteration":86,"passed_time":0.499338577,"remaining_time":5.240185297},
{"learn":[0.5307366632],"iteration":87,"passed_time":0.5051957974,"remaining_time":5.235665536},
{"learn":[0.5296397455],"iteration":88,"passed_time":0.5110360455,"remaining_time":5.230941994},
{"learn":[0.5283568089],"iteration":89,"passed_time":0.5166716527,"remaining_time":5.224124489},
{"learn":[0.5272324337],"iteration":90,"passed_time":0.5222409745,"remaining_time":5.216670833},
{"learn":[0.5266964532],"iteration":91,"passed_time":0.5279518342,"remaining_time":5.21065506},
{"learn":[0.5257317808],"iteration":92,"passed_time":0.5340189799,"remaining_time":5.208120589},
{"learn":[0.5248553366],"iteration":93,"passed_time":0.5402190957,"remaining_time":5.206792561},
{"learn":[0.5243417965],"iteration":94,"passed_time":0.5462859824,"remaining_time":5.20409278},
{"learn":[0.5231095755],"iteration":95,"passed_time":0.5526461861,"remaining_time":5.204084919},
{"learn":[0.5220211267],"iteration":96,"passed_time":0.5583476296,"remaining_time":5.197813501},
{"learn":[0.5214298755],"iteration":97,"passed_time":0.5644628006,"remaining_time":5.195361695},
{"learn":[0.5208949571],"iteration":98,"passed_time":0.5703941322,"remaining_time":5.191162759},
{"learn":[0.5200539388],"iteration":99,"passed_time":0.5766431787,"remaining_time":5.189788608},
{"learn":[0.519601012],"iteration":100,"passed_time":0.5827653298,"remaining_time":5.18718843},
{"learn":[0.5187894861],"iteration":101,"passed_time":0.5886781731,"remaining_time":5.182676465},
{"learn":[0.5179831664],"iteration":102,"passed_time":0.5950412772,"remaining_time":5.182058502},
{"learn":[0.5168660233],"iteration":103,"passed_time":0.6012371811,"remaining_time":5.17988956},
{"learn":[0.5159724978],"iteration":104,"passed_time":0.6070801436,"remaining_time":5.17463551},
{"learn":[0.5150606962],"iteration":105,"passed_time":0.6132196753,"remaining_time":5.171871601},
{"learn":[0.5142392454],"iteration":106,"passed_time":0.6186254067,"remaining_time":5.16292045},
{"learn":[0.5135684278],"iteration":107,"passed_time":0.6242644001,"remaining_time":5.155961527},
{"learn":[0.5125295224],"iteration":108,"passed_time":0.6307784769,"remaining_time":5.156180027},
{"learn":[0.511649189],"iteration":109,"passed_time":0.636976958,"remaining_time":5.15372266},
{"learn":[0.5105430432],"iteration":110,"passed_time":0.6431006931,"remaining_time":5.150599245},
{"learn":[0.509566951],"iteration":111,"passed_time":0.6489218834,"remaining_time":5.145023504},
{"learn":[0.5081632528],"iteration":112,"passed_time":0.6552173549,"remaining_time":5.143166317},
{"learn":[0.5073507641],"iteration":113,"passed_time":0.6613456877,"remaining_time":5.139932274},
{"learn":[0.506811325],"iteration":114,"passed_time":0.667931629,"remaining_time":5.140169493},
{"learn":[0.5060312217],"iteration":115,"passed_time":0.6741110817,"remaining_time":5.137191347},
{"learn":[0.5053318116],"iteration":116,"passed_time":0.6798980152,"remaining_time":5.131196132},
{"learn":[0.5043045603],"iteration":117,"passed_time":0.6853732276,"remaining_time":5.122874464},
{"learn":[0.5037683767],"iteration":118,"passed_time":0.6909496505,"remaining_time":5.115349933},
{"learn":[0.503073537],"iteration":119,"passed_time":0.6971314907,"remaining_time":5.112297599},
{"learn":[0.5022378559],"iteration":120,"passed_time":0.7037054898,"remaining_time":5.11204236},
{"learn":[0.5014949621],"iteration":121,"passed_time":0.7098513851,"remaining_time":5.108602591},
{"learn":[0.5009153831],"iteration":122,"passed_time":0.7155820791,"remaining_time":5.102158401},
{"learn":[0.5005437614],"iteration":123,"passed_time":0.7216817024,"remaining_time":5.098332027},
{"learn":[0.5000963935],"iteration":124,"passed_time":0.7277913821,"remaining_time":5.094539675},
{"learn":[0.4994587272],"iteration":125,"passed_time":0.7339027531,"remaining_time":5.090722271},
{"learn":[0.4985110119],"iteration":126,"passed_time":0.7396228887,"remaining_time":5.084179384},
{"learn":[0.4977910903],"iteration":127,"passed_time":0.7453945362,"remaining_time":5.078000278},
{"learn":[0.4965957127],"iteration":128,"passed_time":0.7511027228,"remaining_time":5.071399004},
{"learn":[0.4958618979],"iteration":129,"passed_time":0.7573769942,"remaining_time":5.068599884},
{"learn":[0.4951815768],"iteration":130,"passed_time":0.7632684719,"remaining_time":5.063208413},
{"learn":[0.4942126667],"iteration":131,"passed_time":0.7698209536,"remaining_time":5.062155968},
{"learn":[0.4934487696],"iteration":132,"passed_time":0.7757790698,"remaining_time":5.057146267},
{"learn":[0.492936082],"iteration":133,"passed_time":0.781384714,"remaining_time":5.049844495},
{"learn":[0.4919845418],"iteration":134,"passed_time":0.7870056297,"remaining_time":5.042665702},
{"learn":[0.4912999524],"iteration":135,"passed_time":0.7934329903,"remaining_time":5.040633115},
{"learn":[0.4908600327],"iteration":136,"passed_time":0.8004027436,"remaining_time":5.041953049},
{"learn":[0.4896506773],"iteration":137,"passed_time":0.806306953,"remaining_time":5.036497054},
{"learn":[0.4887088552],"iteration":138,"passed_time":0.8122784768,"remaining_time":5.031451572},
{"learn":[0.4875364962],"iteration":139,"passed_time":0.8185877457,"remaining_time":5.028467581},
{"learn":[0.4869080536],"iteration":140,"passed_time":0.8248492143,"remaining_time":5.025145213},
{"learn":[0.4864245076],"iteration":141,"passed_time":0.8307909196,"remaining_time":5.019849359},
{"learn":[0.4853343571],"iteration":142,"passed_time":0.8363374687,"remaining_time":5.012176298},
{"learn":[0.4845672554],"iteration":143,"passed_time":0.8419358244,"remaining_time":5.004840734},
{"learn":[0.4841939631],"iteration":144,"passed_time":0.8477756946,"remaining_time":4.998953233},
{"learn":[0.4833773288],"iteration":145,"passed_time":0.8539289865,"remaining_time":4.994899688},
{"learn":[0.482190167],"iteration":146,"passed_time":0.8597789338,"remaining_time":4.989057351},
{"learn":[0.4813592436],"iteration":147,"passed_time":0.8655396984,"remaining_time":4.982701507},
{"learn":[0.4810345163],"iteration":148,"passed_time":0.8713032897,"remaining_time":4.976369796},
{"learn":[0.4803676653],"iteration":149,"passed_time":0.8771637972,"remaining_time":4.970594851},
{"learn":[0.4798026064],"iteration":150,"passed_time":0.8832032094,"remaining_time":4.965824668},
{"learn":[0.4787826692],"iteration":151,"passed_time":0.8895676676,"remaining_time":4.962851198},
{"learn":[0.4780659923],"iteration":152,"passed_time":0.8953626614,"remaining_time":4.956680877},
{"learn":[0.4775570665],"iteration":153,"passed_time":0.9007440746,"remaining_time":4.948243423},
{"learn":[0.477002804],"iteration":154,"passed_time":0.906594336,"remaining_time":4.94240138},
{"learn":[0.4766565012],"iteration":155,"passed_time":0.9129279933,"remaining_time":4.939174528},
{"learn":[0.476028162],"iteration":156,"passed_time":0.919841852,"remaining_time":4.939023447},
{"learn":[0.4752520801],"iteration":157,"passed_time":0.9257678055,"remaining_time":4.933522103},
{"learn":[0.4746966993],"iteration":158,"passed_time":0.9316769385,"remaining_time":4.927926448},
{"learn":[0.4738797012],"iteration":159,"passed_time":0.9382475763,"remaining_time":4.925799776},
{"learn":[0.4728312935],"iteration":160,"passed_time":0.9464289517,"remaining_time":4.932011742},
{"learn":[0.471894756],"iteration":161,"passed_time":0.9533988353,"remaining_time":4.931779161},
{"learn":[0.470840907],"iteration":162,"passed_time":0.9597694955,"remaining_time":4.928386919},
{"learn":[0.4698561358],"iteration":163,"passed_time":0.9654431993,"remaining_time":4.921405577},
{"learn":[0.4692117734],"iteration":164,"passed_time":0.9709249931,"remaining_time":4.913468905},
{"learn":[0.4687295995],"iteration":165,"passed_time":0.9770645796,"remaining_time":4.908866623},
{"learn":[0.4680827893],"iteration":166,"passed_time":0.9833027757,"remaining_time":4.904737797},
{"learn":[0.467593195],"iteration":167,"passed_time":0.990207542,"remaining_time":4.90388497},
{"learn":[0.4669104086],"iteration":168,"passed_time":0.9956101366,"remaining_time":4.895574103},
{"learn":[0.4656998247],"iteration":169,"passed_time":1.00103386,"remaining_time":4.887400609},
{"learn":[0.4653177577],"iteration":170,"passed_time":1.006781548,"remaining_time":4.880829842},
{"learn":[0.4644591005],"iteration":171,"passed_time":1.013180414,"remaining_time":4.877403387},
{"learn":[0.4639380062],"iteration":172,"passed_time":1.020003573,"remaining_time":4.875970839},
{"learn":[0.4631706859],"iteration":173,"passed_time":1.026293452,"remaining_time":4.871944776},
{"learn":[0.4625297761],"iteration":174,"passed_time":1.031656684,"remaining_time":4.863524367},
{"learn":[0.4622873012],"iteration":175,"passed_time":1.036914563,"remaining_time":4.854645456},
{"learn":[0.4615519189],"iteration":176,"passed_time":1.043146719,"remaining_time":4.85033757},
{"learn":[0.461233099],"iteration":177,"passed_time":1.049237494,"remaining_time":4.845355171},
{"learn":[0.4601011798],"iteration":178,"passed_time":1.056165568,"remaining_time":4.844200732},
{"learn":[0.4597781185],"iteration":179,"passed_time":1.061668248,"remaining_time":4.836488686},
{"learn":[0.4591348498],"iteration":180,"passed_time":1.067494987,"remaining_time":4.830267373},
{"learn":[0.4586768253],"iteration":181,"passed_time":1.073769305,"remaining_time":4.82606204},
{"learn":[0.4582647977],"iteration":182,"passed_time":1.080276399,"remaining_time":4.822873323},
{"learn":[0.4577673154],"iteration":183,"passed_time":1.0863512,"remaining_time":4.81773141},
{"learn":[0.4572649877],"iteration":184,"passed_time":1.091945294,"remaining_time":4.810461703},
{"learn":[0.4567950517],"iteration":185,"passed_time":1.09733902,"remaining_time":4.802333129},
{"learn":[0.4562140207],"iteration":186,"passed_time":1.102875635,"remaining_time":4.794855032},
{"learn":[0.455504676],"iteration":187,"passed_time":1.108688229,"remaining_time":4.788589585},
{"learn":[0.4550137093],"iteration":188,"passed_time":1.114595336,"remaining_time":4.782734483},
{"learn":[0.4546338761],"iteration":189,"passed_time":1.120124467,"remaining_time":4.775267464},
{"learn":[0.4543187068],"iteration":190,"passed_time":1.125456261,"remaining_time":4.766984895},
{"learn":[0.4539250847],"iteration":191,"passed_time":1.131631357,"remaining_time":4.762281959},
{"learn":[0.4533435698],"iteration":192,"passed_time":1.138163237,"remaining_time":4.759055607},
{"learn":[0.4529981979],"iteration":193,"passed_time":1.14458238,"remaining_time":4.755326797},
{"learn":[0.4521039225],"iteration":194,"passed_time":1.150383036,"remaining_time":4.749017147},
{"learn":[0.4517583361],"iteration":195,"passed_time":1.155718619,"remaining_time":4.740804946},
{"learn":[0.4509521066],"iteration":196,"passed_time":1.161479822,"remaining_time":4.734356836},
{"learn":[0.4501314693],"iteration":197,"passed_time":1.167653509,"remaining_time":4.729586434},
{"learn":[0.4496342597],"iteration":198,"passed_time":1.174298355,"remaining_time":4.726698402},
{"learn":[0.4491573414],"iteration":199,"passed_time":1.180540706,"remaining_time":4.722162823},
{"learn":[0.4484906527],"iteration":200,"passed_time":1.186072434,"remaining_time":4.714785448},
{"learn":[0.4478207677],"iteration":201,"passed_time":1.191942942,"remaining_time":4.708764691},
{"learn":[0.4471453904],"iteration":202,"passed_time":1.197579724,"remaining_time":4.701827784},
{"learn":[0.446352031],"iteration":203,"passed_time":1.203229999,"remaining_time":4.694956272},
{"learn":[0.4454474372],"iteration":204,"passed_time":1.208494496,"remaining_time":4.686600605},
{"learn":[0.4448683032],"iteration":205,"passed_time":1.213859769,"remaining_time":4.67866338},
{"learn":[0.4444088018],"iteration":206,"passed_time":1.219258755,"remaining_time":4.670880157},
{"learn":[0.4433601202],"iteration":207,"passed_time":1.224542429,"remaining_time":4.662680788},
{"learn":[0.4429849682],"iteration":208,"passed_time":1.229749154,"remaining_time":4.654218089},
{"learn":[0.4428196715],"iteration":209,"passed_time":1.235045381,"remaining_time":4.646123098},
{"learn":[0.4423909861],"iteration":210,"passed_time":1.240739469,"remaining_time":4.639542373},
{"learn":[0.4415420969],"iteration":211,"passed_time":1.246058096,"remaining_time":4.631574433},
{"learn":[0.4413839341],"iteration":212,"passed_time":1.251849237,"remaining_time":4.625377227},
{"learn":[0.4406610887],"iteration":213,"passed_time":1.257624247,"remaining_time":4.61912457},
{"learn":[0.4402349586],"iteration":214,"passed_time":1.263166996,"remaining_time":4.612028333},
{"learn":[0.439666702],"iteration":215,"passed_time":1.268600764,"remaining_time":4.60455092},
{"learn":[0.4388444044],"iteration":216,"passed_time":1.274042443,"remaining_time":4.597120888},
{"learn":[0.4380669593],"iteration":217,"passed_time":1.279572529,"remaining_time":4.590026227},
{"learn":[0.4376310767],"iteration":218,"passed_time":1.286268985,"remaining_time":4.587105377},
{"learn":[0.436963605],"iteration":219,"passed_time":1.292094942,"remaining_time":4.581063886},
{"learn":[0.4366757245],"iteration":220,"passed_time":1.297631323,"remaining_time":4.574003622},
{"learn":[0.4357858462],"iteration":221,"passed_time":1.302909112,"remaining_time":4.566050852},
{"learn":[0.4354283756],"iteration":222,"passed_time":1.308195214,"remaining_time":4.558151037},
{"learn":[0.434899039],"iteration":223,"passed_time":1.313783694,"remaining_time":4.551322083},
{"learn":[0.4345313712],"iteration":224,"passed_time":1.31967341,"remaining_time":4.545541745},
{"learn":[0.4340868397],"iteration":225,"passed_time":1.325183713,"remaining_time":4.538461035},
{"learn":[0.4332855754],"iteration":226,"passed_time":1.330964656,"remaining_time":4.532315768},
{"learn":[0.4327634264],"iteration":227,"passed_time":1.336951278,"remaining_time":4.526870117},
{"learn":[0.432345959],"iteration":228,"passed_time":1.343069527,"remaining_time":4.521862905},
{"learn":[0.4316084336],"iteration":229,"passed_time":1.350564281,"remaining_time":4.521454333},
{"learn":[0.4310776338],"iteration":230,"passed_time":1.356523325,"remaining_time":4.515872021},
{"learn":[0.4306887453],"iteration":231,"passed_time":1.36243517,"remaining_time":4.510130217},
{"learn":[0.4302162684],"iteration":232,"passed_time":1.368385128,"remaining_time":4.504512417},
{"learn":[0.4296207956],"iteration":233,"passed_time":1.373867266,"remaining_time":4.497360368},
{"learn":[0.4285250936],"iteration":234,"passed_time":1.37929535,"remaining_time":4.490046564},
{"learn":[0.4278709041],"iteration":235,"passed_time":1.384611748,"remaining_time":4.482387185},
{"learn":[0.427288062],"iteration":236,"passed_time":1.38998568,"remaining_time":4.474932801},
{"learn":[0.4267744578],"iteration":237,"passed_time":1.39561342,"remaining_time":4.468308514},
{"learn":[0.4262409829],"iteration":238,"passed_time":1.401126188,"remaining_time":4.461326481},
{"learn":[0.4257774431],"iteration":239,"passed_time":1.407125518,"remaining_time":4.455897472},
{"learn":[0.4253538367],"iteration":240,"passed_time":1.413141868,"remaining_time":4.450517336},
{"learn":[0.4246374197],"iteration":241,"passed_time":1.419143417,"remaining_time":4.445085579},
{"learn":[0.4243769349],"iteration":242,"passed_time":1.425839402,"remaining_time":4.441812458},
{"learn":[0.4235369372],"iteration":243,"passed_time":1.432077679,"remaining_time":4.437093136},
{"learn":[0.4230039677],"iteration":244,"passed_time":1.437763355,"remaining_time":4.430658502},
{"learn":[0.4224672051],"iteration":245,"passed_time":1.44341656,"remaining_time":4.424130431},
{"learn":[0.4216620958],"iteration":246,"passed_time":1.449107078,"remaining_time":4.417723197},
{"learn":[0.4210317112],"iteration":247,"passed_time":1.455217274,"remaining_time":4.412594316},
{"learn":[0.4204665851],"iteration":248,"passed_time":1.460632444,"remaining_time":4.405361308},
{"learn":[0.4201531763],"iteration":249,"passed_time":1.466174198,"remaining_time":4.398522593},
{"learn":[0.4193749967],"iteration":250,"passed_time":1.471886477,"remaining_time":4.392203072},
{"learn":[0.4187957806],"iteration":251,"passed_time":1.47781308,"remaining_time":4.386524539},
{"learn":[0.4185301244],"iteration":252,"passed_time":1.483283162,"remaining_time":4.379496135},
{"learn":[0.4180405221],"iteration":253,"passed_time":1.488939382,"remaining_time":4.373026689},
{"learn":[0.4171047381],"iteration":254,"passed_time":1.494434595,"remaining_time":4.366093228},
{"learn":[0.4163645551],"iteration":255,"passed_time":1.499775408,"remaining_time":4.358722279},
{"learn":[0.4159754441],"iteration":256,"passed_time":1.505610653,"remaining_time":4.352796558},
{"learn":[0.4154849772],"iteration":257,"passed_time":1.511799833,"remaining_time":4.347889441},
{"learn":[0.4148779587],"iteration":258,"passed_time":1.518496296,"remaining_time":4.344423764},
{"learn":[0.4144860964],"iteration":259,"passed_time":1.524666384,"remaining_time":4.339435092},
{"learn":[0.414190288],"iteration":260,"passed_time":1.53034509,"remaining_time":4.333046059},
{"learn":[0.4136503853],"iteration":261,"passed_time":1.535742658,"remaining_time":4.325870539},
{"learn":[0.4123093515],"iteration":262,"passed_time":1.541232346,"remaining_time":4.318966687},
{"learn":[0.4119143231],"iteration":263,"passed_time":1.547036798,"remaining_time":4.312951073},
{"learn":[0.4115588821],"iteration":264,"passed_time":1.552851755,"remaining_time":4.306966189},
{"learn":[0.4111665509],"iteration":265,"passed_time":1.558846159,"remaining_time":4.301477747},
{"learn":[0.4105976778],"iteration":266,"passed_time":1.564592734,"remaining_time":4.295305147},
{"learn":[0.4100770429],"iteration":267,"passed_time":1.570004765,"remaining_time":4.28822197},
{"learn":[0.4094259058],"iteration":268,"passed_time":1.575326252,"remaining_time":4.280905167},
{"learn":[0.4088385318],"iteration":269,"passed_time":1.580884721,"remaining_time":4.274243876},
{"learn":[0.4082958055],"iteration":270,"passed_time":1.586324145,"remaining_time":4.267270486},
{"learn":[0.4081623979],"iteration":271,"passed_time":1.591624292,"remaining_time":4.259935604},
{"learn":[0.4078101135],"iteration":272,"passed_time":1.596895911,"remaining_time":4.252539659},
{"learn":[0.4074432374],"iteration":273,"passed_time":1.602085074,"remaining_time":4.244940743},
{"learn":[0.4069141358],"iteration":274,"passed_time":1.607745794,"remaining_time":4.238602548},
{"learn":[0.4061674063],"iteration":275,"passed_time":1.613472038,"remaining_time":4.232441142},
{"learn":[0.4058081327],"iteration":276,"passed_time":1.619293068,"remaining_time":4.226530283},
{"learn":[0.4054840169],"iteration":277,"passed_time":1.624692666,"remaining_time":4.219525558},
{"learn":[0.404679706],"iteration":278,"passed_time":1.630375013,"remaining_time":4.213263028},
{"learn":[0.4042272198],"iteration":279,"passed_time":1.635867951,"remaining_time":4.206517588},
{"learn":[0.4037646499],"iteration":280,"passed_time":1.641525195,"remaining_time":4.200201478},
{"learn":[0.4035375006],"iteration":281,"passed_time":1.646916542,"remaining_time":4.193213039},
{"learn":[0.4029208107],"iteration":282,"passed_time":1.652363271,"remaining_time":4.186376203},
{"learn":[0.4024900268],"iteration":283,"passed_time":1.657661952,"remaining_time":4.179175907},
{"learn":[0.4018338699],"iteration":284,"passed_time":1.663155843,"remaining_time":4.172478693},
{"learn":[0.4013064547],"iteration":285,"passed_time":1.668781932,"remaining_time":4.166119929},
{"learn":[0.4006509439],"iteration":286,"passed_time":1.674428118,"remaining_time":4.159816195},
{"learn":[0.400291643],"iteration":287,"passed_time":1.67987167,"remaining_time":4.153016072},
{"learn":[0.3996563215],"iteration":288,"passed_time":1.685173087,"remaining_time":4.145875658},
{"learn":[0.399323707],"iteration":289,"passed_time":1.690503874,"remaining_time":4.13881983},
{"learn":[0.3988169581],"iteration":290,"passed_time":1.695982509,"remaining_time":4.132136079},
{"learn":[0.3985736204],"iteration":291,"passed_time":1.701243876,"remaining_time":4.12493378},
{"learn":[0.3982105383],"iteration":292,"passed_time":1.706413075,"remaining_time":4.117522336},
{"learn":[0.3978750486],"iteration":293,"passed_time":1.71228525,"remaining_time":4.111814239},
{"learn":[0.3977050105],"iteration":294,"passed_time":1.718207814,"remaining_time":4.106225455},
{"learn":[0.3971227433],"iteration":295,"passed_time":1.724322488,"remaining_time":4.101091324},
{"learn":[0.3967927272],"iteration":296,"passed_time":1.730881342,"remaining_time":4.097001965},
{"learn":[0.3960735945],"iteration":297,"passed_time":1.737015939,"remaining_time":4.091896608},
{"learn":[0.3953422442],"iteration":298,"passed_time":1.743239593,"remaining_time":4.086993159},
{"learn":[0.3949802492],"iteration":299,"passed_time":1.749463824,"remaining_time":4.082082257},
{"learn":[0.3943141132],"iteration":300,"passed_time":1.755107573,"remaining_time":4.075814596},
{"learn":[0.3939923564],"iteration":301,"passed_time":1.760606529,"remaining_time":4.069216414},
{"learn":[0.3934749001],"iteration":302,"passed_time":1.765904243,"remaining_time":4.062162566},
{"learn":[0.3932172888],"iteration":303,"passed_time":1.771582276,"remaining_time":4.055991},
{"learn":[0.3926107845],"iteration":304,"passed_time":1.777996944,"remaining_time":4.051501234},
{"learn":[0.3922134875],"iteration":305,"passed_time":1.783958365,"remaining_time":4.045970933},
{"learn":[0.3919446722],"iteration":306,"passed_time":1.78930108,"remaining_time":4.0390412},
{"learn":[0.3916656749],"iteration":307,"passed_time":1.794527625,"remaining_time":4.031860767},
{"learn":[0.3911434291],"iteration":308,"passed_time":1.799855433,"remaining_time":4.024919431},
{"learn":[0.3907422674],"iteration":309,"passed_time":1.80543632,"remaining_time":4.01855181},
{"learn":[0.3902964193],"iteration":310,"passed_time":1.810831632,"remaining_time":4.011778117},
{"learn":[0.3898037281],"iteration":311,"passed_time":1.816163257,"remaining_time":4.004872824},
{"learn":[0.3894065752],"iteration":312,"passed_time":1.822206031,"remaining_time":3.999538476},
{"learn":[0.3889338941],"iteration":313,"passed_time":1.827874871,"remaining_time":3.993382679},
{"learn":[0.3884461373],"iteration":314,"passed_time":1.833467914,"remaining_time":3.987065146},
{"learn":[0.3882834055],"iteration":315,"passed_time":1.838756451,"remaining_time":3.980093078},
{"learn":[0.3878043187],"iteration":316,"passed_time":1.844035705,"remaining_time":3.973111629},
{"learn":[0.3870373519],"iteration":317,"passed_time":1.850146197,"remaining_time":3.967923605},
{"learn":[0.3867323806],"iteration":318,"passed_time":1.855540779,"remaining_time":3.961201475},
{"learn":[0.3863083128],"iteration":319,"passed_time":1.860985779,"remaining_time":3.95459478},
{"learn":[0.3858648225],"iteration":320,"passed_time":1.866346758,"remaining_time":3.947817597},
{"learn":[0.3856288854],"iteration":321,"passed_time":1.871643574,"remaining_time":3.94091411},
{"learn":[0.385180321],"iteration":322,"passed_time":1.876941908,"remaining_time":3.934023752},
{"learn":[0.3845588608],"iteration":323,"passed_time":1.882791898,"remaining_time":3.928294208},
{"learn":[0.3842248054],"iteration":324,"passed_time":1.888983077,"remaining_time":3.923272544},
{"learn":[0.3836909553],"iteration":325,"passed_time":1.895950464,"remaining_time":3.919848505},
{"learn":[0.3833763515],"iteration":326,"passed_time":1.902067482,"remaining_time":3.914652647},
{"learn":[0.3826537594],"iteration":327,"passed_time":1.907922281,"remaining_time":3.908913942},
{"learn":[0.3821640294],"iteration":328,"passed_time":1.913523173,"remaining_time":3.902656683},
{"learn":[0.3815782031],"iteration":329,"passed_time":1.91903054,"remaining_time":3.896213521},
{"learn":[0.3811285425],"iteration":330,"passed_time":1.924342923,"remaining_time":3.889381919},
{"learn":[0.380464605],"iteration":331,"passed_time":1.929811886,"remaining_time":3.882874517},
{"learn":[0.3801636155],"iteration":332,"passed_time":1.935176129,"remaining_time":3.876163599},
{"learn":[0.3797975581],"iteration":333,"passed_time":1.940850517,"remaining_time":3.870079174},
{"learn":[0.3792910158],"iteration":334,"passed_time":1.946537303,"remaining_time":3.86402181},
{"learn":[0.3791079613],"iteration":335,"passed_time":1.952361215,"remaining_time":3.85823764},
{"learn":[0.3787233172],"iteration":336,"passed_time":1.958025193,"remaining_time":3.852138584},
{"learn":[0.3781105673],"iteration":337,"passed_time":1.963581553,"remaining_time":3.845831325},
{"learn":[0.3775113108],"iteration":338,"passed_time":1.96903645,"remaining_time":3.839330659},
{"learn":[0.3770223095],"iteration":339,"passed_time":1.975185615,"remaining_time":3.834183842},
{"learn":[0.3766536469],"iteration":340,"passed_time":1.981563173,"remaining_time":3.829472526},
{"learn":[0.3761529194],"iteration":341,"passed_time":1.9874041,"remaining_time":3.823718999},
{"learn":[0.375813449],"iteration":342,"passed_time":1.993320893,"remaining_time":3.818110282},
{"learn":[0.3751841518],"iteration":343,"passed_time":2.000556919,"remaining_time":3.815015519},
{"learn":[0.3745937609],"iteration":344,"passed_time":2.006669057,"remaining_time":3.809762993},
{"learn":[0.3741430226],"iteration":345,"passed_time":2.01284408,"remaining_time":3.804624358},
{"learn":[0.373755418],"iteration":346,"passed_time":2.018440722,"remaining_time":3.79839133},
{"learn":[0.3733125402],"iteration":347,"passed_time":2.023893112,"remaining_time":3.791891693},
{"learn":[0.3727704765],"iteration":348,"passed_time":2.028856827,"remaining_time":3.784486518},
{"learn":[0.3724537006],"iteration":349,"passed_time":2.034023042,"remaining_time":3.777471363},
{"learn":[0.3721746714],"iteration":350,"passed_time":2.039215642,"remaining_time":3.770515531},
{"learn":[0.371858434],"iteration":351,"passed_time":2.044117883,"remaining_time":3.763035193},
{"learn":[0.3713040584],"iteration":352,"passed_time":2.049971176,"remaining_time":3.757312609},
{"learn":[0.3709146817],"iteration":353,"passed_time":2.056257147,"remaining_time":3.752378862},
{"learn":[0.3707929973],"iteration":354,"passed_time":2.062398697,"remaining_time":3.747175097},
{"learn":[0.3703492518],"iteration":355,"passed_time":2.068653263,"remaining_time":3.742170509},
{"learn":[0.3697973212],"iteration":356,"passed_time":2.074968229,"remaining_time":3.737267706},
{"learn":[0.3695634104],"iteration":357,"passed_time":2.08062728,"remaining_time":3.731180765},
{"learn":[0.3688331373],"iteration":358,"passed_time":2.086070253,"remaining_time":3.724710397},
{"learn":[0.3685837768],"iteration":359,"passed_time":2.091360939,"remaining_time":3.717975003},
{"learn":[0.3683506393],"iteration":360,"passed_time":2.097267814,"remaining_time":3.712338318},
{"learn":[0.3677533618],"iteration":361,"passed_time":2.102856895,"remaining_time":3.706140052},
{"learn":[0.3674811714],"iteration":362,"passed_time":2.108363098,"remaining_time":3.699799706},
{"learn":[0.3673198518],"iteration":363,"passed_time":2.11371097,"remaining_time":3.6931873},
{"learn":[0.366967438],"iteration":364,"passed_time":2.11917288,"remaining_time":3.686780216},
{"learn":[0.3666764368],"iteration":365,"passed_time":2.124783869,"remaining_time":3.680636538},
{"learn":[0.3665198801],"iteration":366,"passed_time":2.130680191,"remaining_time":3.674987904},
{"learn":[0.3660223707],"iteration":367,"passed_time":2.136400984,"remaining_time":3.669036473},
{"learn":[0.365700435],"iteration":368,"passed_time":2.141726376,"remaining_time":3.662410145},
{"learn":[0.365324971],"iteration":369,"passed_time":2.147125473,"remaining_time":3.655916347},
{"learn":[0.3649766519],"iteration":370,"passed_time":2.152462681,"remaining_time":3.649323521},
{"learn":[0.3646883247],"iteration":371,"passed_time":2.158132214,"remaining_time":3.643298469},
{"learn":[0.3645483226],"iteration":372,"passed_time":2.163348407,"remaining_time":3.636513274},
{"learn":[0.3641857221],"iteration":373,"passed_time":2.168748798,"remaining_time":3.63004478},
{"learn":[0.3637245262],"iteration":374,"passed_time":2.173955938,"remaining_time":3.623259897},
{"learn":[0.3631003143],"iteration":375,"passed_time":2.179274375,"remaining_time":3.616668112},
{"learn":[0.362869491],"iteration":376,"passed_time":2.184584232,"remaining_time":3.610068904},
{"learn":[0.3623707218],"iteration":377,"passed_time":2.190292343,"remaining_time":3.604131845},
{"learn":[0.3621593265],"iteration":378,"passed_time":2.195997424,"remaining_time":3.59819103},
{"learn":[0.3618874556],"iteration":379,"passed_time":2.201808472,"remaining_time":3.592424349},
{"learn":[0.3615227089],"iteration":380,"passed_time":2.20724263,"remaining_time":3.586045112},
{"learn":[0.3609953903],"iteration":381,"passed_time":2.212678277,"remaining_time":3.579673233},
{"learn":[0.3605190576],"iteration":382,"passed_time":2.218435042,"remaining_time":3.573823553},
{"learn":[0.3601210295],"iteration":383,"passed_time":2.224250725,"remaining_time":3.568068872},
{"learn":[0.3591937601],"iteration":384,"passed_time":2.230018253,"remaining_time":3.56223695},
{"learn":[0.3590400748],"iteration":385,"passed_time":2.235920862,"remaining_time":3.556620231},
{"learn":[0.3587259472],"iteration":386,"passed_time":2.242151515,"remaining_time":3.55152165},
{"learn":[0.358043577],"iteration":387,"passed_time":2.248818848,"remaining_time":3.547106018},
{"learn":[0.3576444239],"iteration":388,"passed_time":2.25483775,"remaining_time":3.541660322},
{"learn":[0.3573320376],"iteration":389,"passed_time":2.260496961,"remaining_time":3.535649092},
{"learn":[0.356967851],"iteration":390,"passed_time":2.266541719,"remaining_time":3.530240171},
{"learn":[0.3563163963],"iteration":391,"passed_time":2.271883477,"remaining_time":3.523737638},
{"learn":[0.3559250206],"iteration":392,"passed_time":2.277220866,"remaining_time":3.517234263},
{"learn":[0.3555731226],"iteration":393,"passed_time":2.282550603,"remaining_time":3.510725039},
{"learn":[0.3551134853],"iteration":394,"passed_time":2.287809622,"remaining_time":3.504113472},
{"learn":[0.3546313354],"iteration":395,"passed_time":2.293055601,"remaining_time":3.497488846},
{"learn":[0.354112871],"iteration":396,"passed_time":2.298323321,"remaining_time":3.490904188},
{"learn":[0.3535239793],"iteration":397,"passed_time":2.303676842,"remaining_time":3.484455927},
{"learn":[0.3531823849],"iteration":398,"passed_time":2.30910704,"remaining_time":3.478128649},
{"learn":[0.3528067021],"iteration":399,"passed_time":2.314839458,"remaining_time":3.472259187},
{"learn":[0.3525369117],"iteration":400,"passed_time":2.320364723,"remaining_time":3.46608097},
{"learn":[0.3521897297],"iteration":401,"passed_time":2.325996208,"remaining_time":3.460064012},
{"learn":[0.3519022706],"iteration":402,"passed_time":2.331731017,"remaining_time":3.454202028},
{"learn":[0.351282769],"iteration":403,"passed_time":2.337634446,"remaining_time":3.448589431},
{"learn":[0.3509584481],"iteration":404,"passed_time":2.343606512,"remaining_time":3.443076234},
{"learn":[0.350520104],"iteration":405,"passed_time":2.34935025,"remaining_time":3.43722672},
{"learn":[0.3502680102],"iteration":406,"passed_time":2.355078462,"remaining_time":3.431355106},
{"learn":[0.3500493983],"iteration":407,"passed_time":2.360397708,"remaining_time":3.424890792},
{"learn":[0.3497277118],"iteration":408,"passed_time":2.365651908,"remaining_time":3.418338087},
{"learn":[0.3492587878],"iteration":409,"passed_time":2.371390099,"remaining_time":3.412488191},
{"learn":[0.3488222372],"iteration":410,"passed_time":2.377409606,"remaining_time":3.407041991},
{"learn":[0.3486234718],"iteration":411,"passed_time":2.38302235,"remaining_time":3.401012481},
{"learn":[0.3484063999],"iteration":412,"passed_time":2.388773492,"remaining_time":3.395181695},
{"learn":[0.3481572214],"iteration":413,"passed_time":2.39413026,"remaining_time":3.388793074},
{"learn":[0.3479224095],"iteration":414,"passed_time":2.399728194,"remaining_time":3.382749381},
{"learn":[0.3475348166],"iteration":415,"passed_time":2.405731086,"remaining_time":3.377276333},
{"learn":[0.3471619729],"iteration":416,"passed_time":2.412396033,"remaining_time":3.372726349},
{"learn":[0.3467318166],"iteration":417,"passed_time":2.418897743,"remaining_time":3.367938963},
{"learn":[0.3464665114],"iteration":418,"passed_time":2.424793023,"remaining_time":3.362302497},
{"learn":[0.3459637145],"iteration":419,"passed_time":2.430684217,"remaining_time":3.356659157},
{"learn":[0.3456656597],"iteration":420,"passed_time":2.436075626,"remaining_time":3.350327287},
{"learn":[0.3452853914],"iteration":421,"passed_time":2.441519452,"remaining_time":3.344071667},
{"learn":[0.344810571],"iteration":422,"passed_time":2.447026445,"remaining_time":3.337906049},
{"learn":[0.344485537],"iteration":423,"passed_time":2.453328598,"remaining_time":3.332823756},
{"learn":[0.3441500442],"iteration":424,"passed_time":2.459664127,"remaining_time":3.327780878},
{"learn":[0.3438178604],"iteration":425,"passed_time":2.465611753,"remaining_time":3.322209264},
{"learn":[0.3434626854],"iteration":426,"passed_time":2.471627868,"remaining_time":3.316727794},
{"learn":[0.3432634093],"iteration":427,"passed_time":2.477170134,"remaining_time":3.310610553},
{"learn":[0.3430354172],"iteration":428,"passed_time":2.483254532,"remaining_time":3.30521757},
{"learn":[0.3427529472],"iteration":429,"passed_time":2.489370734,"remaining_time":3.299863531},
{"learn":[0.3421263375],"iteration":430,"passed_time":2.495493834,"remaining_time":3.294515062},
{"learn":[0.3417253327],"iteration":431,"passed_time":2.501152862,"remaining_time":3.288552837},
{"learn":[0.3414353369],"iteration":432,"passed_time":2.506530213,"remaining_time":3.282223166},
{"learn":[0.3410152231],"iteration":433,"passed_time":2.511841719,"remaining_time":3.275812012},
{"learn":[0.3406303011],"iteration":434,"passed_time":2.517151696,"remaining_time":3.269403927},
{"learn":[0.340209789],"iteration":435,"passed_time":2.522587772,"remaining_time":3.263163999},
{"learn":[0.3399691063],"iteration":436,"passed_time":2.528249738,"remaining_time":3.25721877},
{"learn":[0.3395809999],"iteration":437,"passed_time":2.533464104,"remaining_time":3.250700516},
{"learn":[0.3393665144],"iteration":438,"passed_time":2.538718522,"remaining_time":3.244239387},
{"learn":[0.3388499726],"iteration":439,"passed_time":2.544415667,"remaining_time":3.238347213},
{"learn":[0.3382950389],"iteration":440,"passed_time":2.550503312,"remaining_time":3.232950911},
{"learn":[0.3378812401],"iteration":441,"passed_time":2.556094237,"remaining_time":3.226924399},
{"learn":[0.3376190042],"iteration":442,"passed_time":2.561487023,"remaining_time":3.220650727},
{"learn":[0.3371352086],"iteration":443,"passed_time":2.566790189,"remaining_time":3.214268796},
{"learn":[0.3367688981],"iteration":444,"passed_time":2.572596935,"remaining_time":3.208519773},
{"learn":[0.3362680253],"iteration":445,"passed_time":2.578853358,"remaining_time":3.203329059},
{"learn":[0.3358519043],"iteration":446,"passed_time":2.585748067,"remaining_time":3.198923223},
{"learn":[0.3354090583],"iteration":447,"passed_time":2.59207685,"remaining_time":3.193808976},
{"learn":[0.3350208421],"iteration":448,"passed_time":2.597926253,"remaining_time":3.188101036},
{"learn":[0.334672506],"iteration":449,"passed_time":2.603575224,"remaining_time":3.182147496},
{"learn":[0.3342919674],"iteration":450,"passed_time":2.609261404,"remaining_time":3.1762406},
{"learn":[0.3336022589],"iteration":451,"passed_time":2.614859595,"remaining_time":3.170228004},
{"learn":[0.3332707412],"iteration":452,"passed_time":2.620325528,"remaining_time":3.164057536},
{"learn":[0.3330055515],"iteration":453,"passed_time":2.625686273,"remaining_time":3.157763668},
{"learn":[0.3325732154],"iteration":454,"passed_time":2.631012797,"remaining_time":3.151432911},
{"learn":[0.3323710108],"iteration":455,"passed_time":2.636604097,"remaining_time":3.145422432},
{"learn":[0.3320695881],"iteration":456,"passed_time":2.642111837,"remaining_time":3.139314503},
{"learn":[0.3318578117],"iteration":457,"passed_time":2.647466447,"remaining_time":3.133027979},
{"learn":[0.3312034262],"iteration":458,"passed_time":2.652813863,"remaining_time":3.126737037},
{"learn":[0.330831358],"iteration":459,"passed_time":2.658009941,"remaining_time":3.120272539},
{"learn":[0.3303246421],"iteration":460,"passed_time":2.663336402,"remaining_time":3.113965988},
{"learn":[0.3298637536],"iteration":461,"passed_time":2.669118005,"remaining_time":3.108193695},
{"learn":[0.3293859847],"iteration":462,"passed_time":2.675035443,"remaining_time":3.102578904},
{"learn":[0.3290371127],"iteration":463,"passed_time":2.680535186,"remaining_time":3.096480301},
{"learn":[0.3284575571],"iteration":464,"passed_time":2.686184392,"remaining_time":3.090556235},
{"learn":[0.327998979],"iteration":465,"passed_time":2.691453989,"remaining_time":3.084198348},
{"learn":[0.3275290623],"iteration":466,"passed_time":2.696922937,"remaining_time":3.078072645},
{"learn":[0.3272763452],"iteration":467,"passed_time":2.702328229,"remaining_time":3.071877389},
{"learn":[0.3269178234],"iteration":468,"passed_time":2.707707284,"remaining_time":3.065655794},
{"learn":[0.3267653229],"iteration":469,"passed_time":2.713329335,"remaining_time":3.059711803},
{"learn":[0.3262716118],"iteration":470,"passed_time":2.719547209,"remaining_time":3.054438373},
{"learn":[0.3260201599],"iteration":471,"passed_time":2.726107155,"remaining_time":3.049543598},
{"learn":[0.3257577677],"iteration":472,"passed_time":2.732775092,"remaining_time":3.044762101},
{"learn":[0.3251354832],"iteration":473,"passed_time":2.739157399,"remaining_time":3.039655679},
{"learn":[0.324827372],"iteration":474,"passed_time":2.745075364,"remaining_time":3.034030665},
{"learn":[0.3244926258],"iteration":475,"passed_time":2.750598387,"remaining_time":3.027969653},
{"learn":[0.3243029246],"iteration":476,"passed_time":2.75630715,"remaining_time":3.022114548},
{"learn":[0.3241041535],"iteration":477,"passed_time":2.761806554,"remaining_time":3.016031425},
{"learn":[0.3239116321],"iteration":478,"passed_time":2.767112789,"remaining_time":3.009740633},
{"learn":[0.3235802959],"iteration":479,"passed_time":2.772564728,"remaining_time":3.003611789},
{"learn":[0.3232985771],"iteration":480,"passed_time":2.777903835,"remaining_time":2.997364013},
{"learn":[0.3230088338],"iteration":481,"passed_time":2.783213385,"remaining_time":2.991088243},
{"learn":[0.3223071419],"iteration":482,"passed_time":2.788921422,"remaining_time":2.985243012},
{"learn":[0.3221371763],"iteration":483,"passed_time":2.794673732,"remaining_time":2.979445549},
{"learn":[0.3218928529],"iteration":484,"passed_time":2.800315334,"remaining_time":2.973530716},
{"learn":[0.3214436556],"iteration":485,"passed_time":2.805600016,"remaining_time":2.967239523},
{"learn":[0.3212624807],"iteration":486,"passed_time":2.81086665,"remaining_time":2.960933452},
{"learn":[0.3209748263],"iteration":487,"passed_time":2.816517375,"remaining_time":2.955034623},
{"learn":[0.320700917],"iteration":488,"passed_time":2.822687137,"remaining_time":2.949679197},
{"learn":[0.3203882068],"iteration":489,"passed_time":2.828946249,"remaining_time":2.944413443},
{"learn":[0.3199099482],"iteration":490,"passed_time":2.834487318,"remaining_time":2.938399277},
{"learn":[0.3196786404],"iteration":491,"passed_time":2.839842716,"remaining_time":2.932195324},
{"learn":[0.3194078089],"iteration":492,"passed_time":2.845066357,"remaining_time":2.925859317},
{"learn":[0.3189553001],"iteration":493,"passed_time":2.850671601,"remaining_time":2.919918684},
{"learn":[0.3185641036],"iteration":494,"passed_time":2.856403012,"remaining_time":2.914108124},
{"learn":[0.3183229066],"iteration":495,"passed_time":2.861851204,"remaining_time":2.908010094},
{"learn":[0.317860242],"iteration":496,"passed_time":2.867182753,"remaining_time":2.901796629},
{"learn":[0.3175860592],"iteration":497,"passed_time":2.872374444,"remaining_time":2.895445724},
{"learn":[0.3172992807],"iteration":498,"passed_time":2.87764533,"remaining_time":2.889178979},
{"learn":[0.3170492124],"iteration":499,"passed_time":2.882921044,"remaining_time":2.882921044},
{"learn":[0.3166465108],"iteration":500,"passed_time":2.888191794,"remaining_time":2.876662087},
{"learn":[0.316147175],"iteration":501,"passed_time":2.893685551,"remaining_time":2.870628296},
{"learn":[0.3159094636],"iteration":502,"passed_time":2.899757169,"remaining_time":2.86516762},
{"learn":[0.3155684204],"iteration":503,"passed_time":2.905558388,"remaining_time":2.859438414},
{"learn":[0.3151887438],"iteration":504,"passed_time":2.911123548,"remaining_time":2.853477537},
{"learn":[0.3148880154],"iteration":505,"passed_time":2.916578181,"remaining_time":2.847410319},
{"learn":[0.3146809027],"iteration":506,"passed_time":2.921934677,"remaining_time":2.84125009},
{"learn":[0.3143395742],"iteration":507,"passed_time":2.927549443,"remaining_time":2.835343162},
{"learn":[0.3140909745],"iteration":508,"passed_time":2.93338244,"remaining_time":2.829647894},
{"learn":[0.313921662],"iteration":509,"passed_time":2.939032789,"remaining_time":2.823776601},
{"learn":[0.313470924],"iteration":510,"passed_time":2.944538073,"remaining_time":2.817767353},
{"learn":[0.3128240665],"iteration":511,"passed_time":2.949796276,"remaining_time":2.811524576},
{"learn":[0.312264659],"iteration":512,"passed_time":2.955541732,"remaining_time":2.805748194},
{"learn":[0.3118859931],"iteration":513,"passed_time":2.96143314,"remaining_time":2.800109934},
{"learn":[0.3115719181],"iteration":514,"passed_time":2.967497608,"remaining_time":2.79463367},
{"learn":[0.3112215943],"iteration":515,"passed_time":2.972909172,"remaining_time":2.788542712},
{"learn":[0.3108336706],"iteration":516,"passed_time":2.978197036,"remaining_time":2.782338817},
{"learn":[0.3104737392],"iteration":517,"passed_time":2.983654656,"remaining_time":2.776296417},
{"learn":[0.3102412988],"iteration":518,"passed_time":2.989035079,"remaining_time":2.770184726},
{"learn":[0.3099757345],"iteration":519,"passed_time":2.99440422,"remaining_time":2.764065434},
{"learn":[0.3096234043],"iteration":520,"passed_time":2.999780421,"remaining_time":2.757955512},
{"learn":[0.309510985],"iteration":521,"passed_time":3.005563791,"remaining_time":2.75222125},
{"learn":[0.3093169775],"iteration":522,"passed_time":3.011424081,"remaining_time":2.746556953},
{"learn":[0.3090218971],"iteration":523,"passed_time":3.017157121,"remaining_time":2.740776316},
{"learn":[0.3087249052],"iteration":524,"passed_time":3.023103545,"remaining_time":2.735188921},
{"learn":[0.3084022143],"iteration":525,"passed_time":3.029082445,"remaining_time":2.729629428},
{"learn":[0.3081778958],"iteration":526,"passed_time":3.035593267,"remaining_time":2.72454576},
{"learn":[0.3080804017],"iteration":527,"passed_time":3.041914314,"remaining_time":2.719287038},
{"learn":[0.3078684262],"iteration":528,"passed_time":3.047843135,"remaining_time":2.713675079},
{"learn":[0.3074510045],"iteration":529,"passed_time":3.054070643,"remaining_time":2.708326797},
{"learn":[0.3072464659],"iteration":530,"passed_time":3.062293695,"remaining_time":2.704737746},
{"learn":[0.3070513186],"iteration":531,"passed_time":3.069757281,"remaining_time":2.700463172},
{"learn":[0.3066187104],"iteration":532,"passed_time":3.075460502,"remaining_time":2.694634249},
{"learn":[0.3060966491],"iteration":533,"passed_time":3.080932896,"remaining_time":2.688604362},
{"learn":[0.3056606126],"iteration":534,"passed_time":3.085981534,"remaining_time":2.682208249},
{"learn":[0.3052960781],"iteration":535,"passed_time":3.091056741,"remaining_time":2.675840164},
{"learn":[0.3050546863],"iteration":536,"passed_time":3.096013021,"remaining_time":2.669374355},
{"learn":[0.3046763436],"iteration":537,"passed_time":3.101008019,"remaining_time":2.662947406},
{"learn":[0.3042616969],"iteration":538,"passed_time":3.105863569,"remaining_time":2.656406503},
{"learn":[0.3040101039],"iteration":539,"passed_time":3.111408983,"remaining_time":2.650459504},
{"learn":[0.3034721184],"iteration":540,"passed_time":3.117053511,"remaining_time":2.64459808},
{"learn":[0.303165881],"iteration":541,"passed_time":3.12236003,"remaining_time":2.638451834},
{"learn":[0.3029202753],"iteration":542,"passed_time":3.127939611,"remaining_time":2.632538494},
{"learn":[0.302478638],"iteration":543,"passed_time":3.133427228,"remaining_time":2.626549294},
{"learn":[0.3019544879],"iteration":544,"passed_time":3.138975667,"remaining_time":2.620612713},
{"learn":[0.301603066],"iteration":545,"passed_time":3.144366649,"remaining_time":2.614546627},
{"learn":[0.3013049958],"iteration":546,"passed_time":3.149642137,"remaining_time":2.608387364},
{"learn":[0.3010893246],"iteration":547,"passed_time":3.154912375,"remaining_time":2.602226995},
{"learn":[0.3008366474],"iteration":548,"passed_time":3.160488134,"remaining_time":2.596320853},
{"learn":[0.3003430607],"iteration":549,"passed_time":3.166071815,"remaining_time":2.590422394},
{"learn":[0.3001077704],"iteration":550,"passed_time":3.171672643,"remaining_time":2.58453905},
{"learn":[0.299723751],"iteration":551,"passed_time":3.177131058,"remaining_time":2.578541148},
{"learn":[0.2994812911],"iteration":552,"passed_time":3.18250131,"remaining_time":2.572473934},
{"learn":[0.2992047359],"iteration":553,"passed_time":3.187838325,"remaining_time":2.566382478},
{"learn":[0.2990445194],"iteration":554,"passed_time":3.193646812,"remaining_time":2.560671768},
{"learn":[0.2986789032],"iteration":555,"passed_time":3.199489495,"remaining_time":2.554988014},
{"learn":[0.2981967513],"iteration":556,"passed_time":3.204998162,"remaining_time":2.549038035},
{"learn":[0.2978670118],"iteration":557,"passed_time":3.21065675,"remaining_time":2.543208393},
{"learn":[0.2972941895],"iteration":558,"passed_time":3.215968068,"remaining_time":2.537105399},
{"learn":[0.2970440388],"iteration":559,"passed_time":3.221772001,"remaining_time":2.531392287},
{"learn":[0.2965965398],"iteration":560,"passed_time":3.227352724,"remaining_time":2.525504181},
{"learn":[0.2960780626],"iteration":561,"passed_time":3.232902035,"remaining_time":2.519592689},
{"learn":[0.2958652204],"iteration":562,"passed_time":3.238502074,"remaining_time":2.513721858},
{"learn":[0.2955103547],"iteration":563,"passed_time":3.244245182,"remaining_time":2.507962588},
{"learn":[0.2949647608],"iteration":564,"passed_time":3.250103727,"remaining_time":2.50229225},
{"learn":[0.2948121009],"iteration":565,"passed_time":3.255705605,"remaining_time":2.496424439},
{"learn":[0.2945896486],"iteration":566,"passed_time":3.261174296,"remaining_time":2.490455856},
{"learn":[0.294068426],"iteration":567,"passed_time":3.266729832,"remaining_time":2.484555084},
{"learn":[0.2937732129],"iteration":568,"passed_time":3.272496604,"remaining_time":2.478815529},
{"learn":[0.2934714695],"iteration":569,"passed_time":3.278271659,"remaining_time":2.473082128},
{"learn":[0.2928517603],"iteration":570,"passed_time":3.284019854,"remaining_time":2.467328402},
{"learn":[0.2925108065],"iteration":571,"passed_time":3.289381109,"remaining_time":2.461285166},
{"learn":[0.2921752859],"iteration":572,"passed_time":3.294770222,"remaining_time":2.455265069},
{"learn":[0.2918632147],"iteration":573,"passed_time":3.300921301,"remaining_time":2.449812673},
{"learn":[0.2916912426],"iteration":574,"passed_time":3.307065219,"remaining_time":2.444352553},
{"learn":[0.2912023195],"iteration":575,"passed_time":3.313154274,"remaining_time":2.438849674},
{"learn":[0.2908565589],"iteration":576,"passed_time":3.31870207,"remaining_time":2.432947964},
{"learn":[0.2906039703],"iteration":577,"passed_time":3.324164594,"remaining_time":2.426985222},
{"learn":[0.2903882943],"iteration":578,"passed_time":3.329892984,"remaining_time":2.421217524},
{"learn":[0.2901461798],"iteration":579,"passed_time":3.335941088,"remaining_time":2.415681478},
{"learn":[0.2897652546],"iteration":580,"passed_time":3.342580214,"remaining_time":2.410569896},
{"learn":[0.2896366999],"iteration":581,"passed_time":3.348540223,"remaining_time":2.404965315},
{"learn":[0.2893242933],"iteration":582,"passed_time":3.355323648,"remaining_time":2.399948476},
{"learn":[0.2890594178],"iteration":583,"passed_time":3.361533459,"remaining_time":2.394516985},
{"learn":[0.2886590251],"iteration":584,"passed_time":3.367434693,"remaining_time":2.388863928},
{"learn":[0.2881802698],"iteration":585,"passed_time":3.373205057,"remaining_time":2.383117566},
{"learn":[0.2877396338],"iteration":586,"passed_time":3.378775439,"remaining_time":2.37723042},
{"learn":[0.2874663128],"iteration":587,"passed_time":3.384483171,"remaining_time":2.371440589},
{"learn":[0.2872697884],"iteration":588,"passed_time":3.390303936,"remaining_time":2.365729911},
{"learn":[0.2869672123],"iteration":589,"passed_time":3.396145947,"remaining_time":2.360033624},
{"learn":[0.2865923724],"iteration":590,"passed_time":3.401848209,"remaining_time":2.354240131},
{"learn":[0.2863810842],"iteration":591,"passed_time":3.407213621,"remaining_time":2.348214793},
{"learn":[0.2860156269],"iteration":592,"passed_time":3.412498536,"remaining_time":2.342136432},
{"learn":[0.2857860008],"iteration":593,"passed_time":3.41783246,"remaining_time":2.33609424},
{"learn":[0.2852638011],"iteration":594,"passed_time":3.42363915,"remaining_time":2.330376228},
{"learn":[0.284922545],"iteration":595,"passed_time":3.429501062,"remaining_time":2.324695351},
{"learn":[0.2845028314],"iteration":596,"passed_time":3.435061946,"remaining_time":2.31881066},
{"learn":[0.2840449622],"iteration":597,"passed_time":3.440729788,"remaining_time":2.312998955},
{"learn":[0.2837408971],"iteration":598,"passed_time":3.446307253,"remaining_time":2.307127226},
{"learn":[0.2835778478],"iteration":599,"passed_time":3.451625942,"remaining_time":2.301083961},
{"learn":[0.2834375662],"iteration":600,"passed_time":3.456892411,"remaining_time":2.295008439},
{"learn":[0.2830048241],"iteration":601,"passed_time":3.46219977,"remaining_time":2.288962639},
{"learn":[0.2827098593],"iteration":602,"passed_time":3.467842576,"remaining_time":2.283140137},
{"learn":[0.2821432325],"iteration":603,"passed_time":3.473324884,"remaining_time":2.277213004},
{"learn":[0.2819190215],"iteration":604,"passed_time":3.478918839,"remaining_time":2.271360234},
{"learn":[0.2814806207],"iteration":605,"passed_time":3.48466343,"remaining_time":2.265606256},
{"learn":[0.2812238354],"iteration":606,"passed_time":3.490677494,"remaining_time":2.26002678},
{"learn":[0.2809844414],"iteration":607,"passed_time":3.49643881,"remaining_time":2.254282917},
{"learn":[0.2807311488],"iteration":608,"passed_time":3.502284382,"remaining_time":2.248593092},
{"learn":[0.2804240979],"iteration":609,"passed_time":3.508124945,"remaining_time":2.242899555},
{"learn":[0.2802737588],"iteration":610,"passed_time":3.513963714,"remaining_time":2.237204394},
{"learn":[0.27995074],"iteration":611,"passed_time":3.519924743,"remaining_time":2.231586275},
{"learn":[0.279863075],"iteration":612,"passed_time":3.525667304,"remaining_time":2.225829113},
{"learn":[0.279553328],"iteration":613,"passed_time":3.531837204,"remaining_time":2.220340653},
{"learn":[0.2791829794],"iteration":614,"passed_time":3.538279648,"remaining_time":2.215020592},
{"learn":[0.2789903105],"iteration":615,"passed_time":3.544191216,"remaining_time":2.209365953},
{"learn":[0.2786234022],"iteration":616,"passed_time":3.550194095,"remaining_time":2.203767161},
{"learn":[0.2784194827],"iteration":617,"passed_time":3.556132628,"remaining_time":2.198127288},
{"learn":[0.2781769526],"iteration":618,"passed_time":3.561955186,"remaining_time":2.192415066},
{"learn":[0.2779065756],"iteration":619,"passed_time":3.567330265,"remaining_time":2.186428227},
{"learn":[0.2774725096],"iteration":620,"passed_time":3.572646489,"remaining_time":2.180407439},
{"learn":[0.2771147272],"iteration":621,"passed_time":3.578132377,"remaining_time":2.174492023},
{"learn":[0.2767788822],"iteration":622,"passed_time":3.583563348,"remaining_time":2.168544755},
{"learn":[0.2766264623],"iteration":623,"passed_time":3.58892137,"remaining_time":2.162555184},
{"learn":[0.2762916942],"iteration":624,"passed_time":3.594435052,"remaining_time":2.156661031},
{"learn":[0.2759725319],"iteration":625,"passed_time":3.600173914,"remaining_time":2.150902626},
{"learn":[0.2757286315],"iteration":626,"passed_time":3.605767524,"remaining_time":2.145057873},
{"learn":[0.275533516],"iteration":627,"passed_time":3.611274965,"remaining_time":2.139162877},
{"learn":[0.2751763078],"iteration":628,"passed_time":3.616702805,"remaining_time":2.133222163},
{"learn":[0.2747848596],"iteration":629,"passed_time":3.622389668,"remaining_time":2.127435202},
{"learn":[0.2743650444],"iteration":630,"passed_time":3.628067966,"remaining_time":2.121643549},
{"learn":[0.2740433354],"iteration":631,"passed_time":3.633570105,"remaining_time":2.115749681},
{"learn":[0.2737427168],"iteration":632,"passed_time":3.638934447,"remaining_time":2.10977716},
{"learn":[0.2735917077],"iteration":633,"passed_time":3.644232734,"remaining_time":2.103768424},
{"learn":[0.2731695146],"iteration":634,"passed_time":3.649510838,"remaining_time":2.097750324},
{"learn":[0.2729153983],"iteration":635,"passed_time":3.655317734,"remaining_time":2.092037194},
{"learn":[0.2725955392],"iteration":636,"passed_time":3.660990596,"remaining_time":2.086247388},
{"learn":[0.2723087169],"iteration":637,"passed_time":3.6663407,"remaining_time":2.080274817},
{"learn":[0.2720571473],"iteration":638,"passed_time":3.671599803,"remaining_time":2.074252784},
{"learn":[0.2717943766],"iteration":639,"passed_time":3.676977737,"remaining_time":2.068299977},
{"learn":[0.2714950225],"iteration":640,"passed_time":3.682322301,"remaining_time":2.062330275},
{"learn":[0.2711714518],"iteration":641,"passed_time":3.687494067,"remaining_time":2.056266162},
{"learn":[0.2710503429],"iteration":642,"passed_time":3.692743381,"remaining_time":2.05024788},
{"learn":[0.2709071178],"iteration":643,"passed_time":3.697923356,"remaining_time":2.044193657},
{"learn":[0.2705196541],"iteration":644,"passed_time":3.703170838,"remaining_time":2.038179299},
{"learn":[0.2701563605],"iteration":645,"passed_time":3.708369748,"remaining_time":2.032140698},
{"learn":[0.2698986537],"iteration":646,"passed_time":3.713926919,"remaining_time":2.026300158},
{"learn":[0.2696047167],"iteration":647,"passed_time":3.719594604,"remaining_time":2.020520526},
{"learn":[0.2693492631],"iteration":648,"passed_time":3.72524475,"remaining_time":2.014731752},
{"learn":[0.2689450115],"iteration":649,"passed_time":3.730637856,"remaining_time":2.008804999},
{"learn":[0.2687944738],"iteration":650,"passed_time":3.73634055,"remaining_time":2.003045856},
{"learn":[0.2686481815],"iteration":651,"passed_time":3.74192189,"remaining_time":1.997222113},
{"learn":[0.2684511204],"iteration":652,"passed_time":3.747770357,"remaining_time":1.991541063},
{"learn":[0.2682002717],"iteration":653,"passed_time":3.753549589,"remaining_time":1.985822871},
{"learn":[0.2679118973],"iteration":654,"passed_time":3.759316084,"remaining_time":1.980097785},
{"learn":[0.2676473519],"iteration":655,"passed_time":3.764859498,"remaining_time":1.97425559},
{"learn":[0.2674172138],"iteration":656,"passed_time":3.770218634,"remaining_time":1.9683181},
{"learn":[0.2672811199],"iteration":657,"passed_time":3.775943582,"remaining_time":1.9625725},
{"learn":[0.267027428],"iteration":658,"passed_time":3.783003243,"remaining_time":1.957517612},
{"learn":[0.2667727549],"iteration":659,"passed_time":3.789048799,"remaining_time":1.95193423},
{"learn":[0.2664888946],"iteration":660,"passed_time":3.79520113,"remaining_time":1.94640421},
{"learn":[0.2663178863],"iteration":661,"passed_time":3.80093905,"remaining_time":1.940660723},
{"learn":[0.2660785912],"iteration":662,"passed_time":3.806341683,"remaining_time":1.934746828},
{"learn":[0.2656278683],"iteration":663,"passed_time":3.811626108,"remaining_time":1.928774657},
{"learn":[0.2653506339],"iteration":664,"passed_time":3.817052474,"remaining_time":1.922876058},
{"learn":[0.2651053695],"iteration":665,"passed_time":3.822627579,"remaining_time":1.91705347},
{"learn":[0.2649554559],"iteration":666,"passed_time":3.828162223,"remaining_time":1.911211425},
{"learn":[0.2646833686],"iteration":667,"passed_time":3.833502221,"remaining_time":1.905273559},
{"learn":[0.2644635651],"iteration":668,"passed_time":3.839181971,"remaining_time":1.899505579},
{"learn":[0.2642033802],"iteration":669,"passed_time":3.844953237,"remaining_time":1.893782938},
{"learn":[0.2637480306],"iteration":670,"passed_time":3.850511658,"remaining_time":1.88795579},
{"learn":[0.2634855859],"iteration":671,"passed_time":3.85588778,"remaining_time":1.882040464},
{"learn":[0.2633572005],"iteration":672,"passed_time":3.86127065,"remaining_time":1.876130019},
{"learn":[0.263075904],"iteration":673,"passed_time":3.866661978,"remaining_time":1.870225229},
{"learn":[0.2629163775],"iteration":674,"passed_time":3.872487467,"remaining_time":1.864531002},
{"learn":[0.2626707032],"iteration":675,"passed_time":3.878268355,"remaining_time":1.858815011},
{"learn":[0.262522286],"iteration":676,"passed_time":3.883865928,"remaining_time":1.853011366},
{"learn":[0.2621659344],"iteration":677,"passed_time":3.889569883,"remaining_time":1.847258853},
{"learn":[0.2619194904],"iteration":678,"passed_time":3.894885809,"remaining_time":1.841323041},
{"learn":[0.2617484278],"iteration":679,"passed_time":3.900362253,"remaining_time":1.83546459},
{"learn":[0.2616157275],"iteration":680,"passed_time":3.90602287,"remaining_time":1.829693532},
{"learn":[0.2612645873],"iteration":681,"passed_time":3.911461309,"remaining_time":1.823819203},
{"learn":[0.260973913],"iteration":682,"passed_time":3.916891171,"remaining_time":1.817942168},
{"learn":[0.2607454985],"iteration":683,"passed_time":3.922234238,"remaining_time":1.812026344},
{"learn":[0.2603578078],"iteration":684,"passed_time":3.927560986,"remaining_time":1.806104687},
{"learn":[0.2602778323],"iteration":685,"passed_time":3.932964103,"remaining_time":1.800219721},
{"learn":[0.2599939672],"iteration":686,"passed_time":3.938353024,"remaining_time":1.794329689},
{"learn":[0.259883435],"iteration":687,"passed_time":3.943704757,"remaining_time":1.78842425},
{"learn":[0.2596493163],"iteration":688,"passed_time":3.950409374,"remaining_time":1.783131082},
{"learn":[0.259441259],"iteration":689,"passed_time":3.957003115,"remaining_time":1.777784008},
{"learn":[0.2593145523],"iteration":690,"passed_time":3.96313946,"remaining_time":1.772228789},
{"learn":[0.2591787742],"iteration":691,"passed_time":3.969424382,"remaining_time":1.76673802},
{"learn":[0.2588525614],"iteration":692,"passed_time":3.974791476,"remaining_time":1.760838359},
{"learn":[0.2586392098],"iteration":693,"passed_time":3.980405422,"remaining_time":1.755049076},
{"learn":[0.2582881984],"iteration":694,"passed_time":3.985996931,"remaining_time":1.749250452},
{"learn":[0.25799402],"iteration":695,"passed_time":3.991739039,"remaining_time":1.743518201},
{"learn":[0.2577379511],"iteration":696,"passed_time":3.997311631,"remaining_time":1.73771223},
{"learn":[0.2573763326],"iteration":697,"passed_time":4.002689298,"remaining_time":1.73182259},
{"learn":[0.2571662243],"iteration":698,"passed_time":4.008180186,"remaining_time":1.72598317},
{"learn":[0.2568247017],"iteration":699,"passed_time":4.013815772,"remaining_time":1.72020676},
{"learn":[0.2565448776],"iteration":700,"passed_time":4.019675644,"remaining_time":1.714526416},
{"learn":[0.2562427979],"iteration":701,"passed_time":4.025653713,"remaining_time":1.708895736},
{"learn":[0.2559522839],"iteration":702,"passed_time":4.031298916,"remaining_time":1.70312344},
{"learn":[0.2556070842],"iteration":703,"passed_time":4.036811023,"remaining_time":1.697295544},
{"learn":[0.2553082103],"iteration":704,"passed_time":4.042234645,"remaining_time":1.691431518},
{"learn":[0.2550104872],"iteration":705,"passed_time":4.047580596,"remaining_time":1.685536395},
{"learn":[0.2548134026],"iteration":706,"passed_time":4.052935492,"remaining_time":1.679646534},
{"learn":[0.2544952718],"iteration":707,"passed_time":4.059656151,"remaining_time":1.674321463},
{"learn":[0.2542933558],"iteration":708,"passed_time":4.066484728,"remaining_time":1.66903675},
{"learn":[0.2540922061],"iteration":709,"passed_time":4.072887887,"remaining_time":1.663573926},
{"learn":[0.2538549021],"iteration":710,"passed_time":4.078974033,"remaining_time":1.6579796},
{"learn":[0.2537405157],"iteration":711,"passed_time":4.084758445,"remaining_time":1.652261843},
{"learn":[0.2534753653],"iteration":712,"passed_time":4.091274501,"remaining_time":1.646838404},
{"learn":[0.2533382929],"iteration":713,"passed_time":4.097442925,"remaining_time":1.641272656},
{"learn":[0.2530969224],"iteration":714,"passed_time":4.103367391,"remaining_time":1.635607981},
{"learn":[0.2527477409],"iteration":715,"passed_time":4.109108531,"remaining_time":1.629869864},
{"learn":[0.2523925318],"iteration":716,"passed_time":4.114598485,"remaining_time":1.624032596},
{"learn":[0.2520727393],"iteration":717,"passed_time":4.120810126,"remaining_time":1.618479743},
{"learn":[0.2518773084],"iteration":718,"passed_time":4.126903986,"remaining_time":1.612879027},
{"learn":[0.2516346367],"iteration":719,"passed_time":4.134225842,"remaining_time":1.607754494},
{"learn":[0.2513610444],"iteration":720,"passed_time":4.140782516,"remaining_time":1.60232777},
{"learn":[0.2511454365],"iteration":721,"passed_time":4.145857035,"remaining_time":1.596327224},
{"learn":[0.2509431277],"iteration":722,"passed_time":4.150920028,"remaining_time":1.590324824},
{"learn":[0.2507228947],"iteration":723,"passed_time":4.155829533,"remaining_time":1.584266507},
{"learn":[0.2504611069],"iteration":724,"passed_time":4.160767257,"remaining_time":1.578222063},
{"learn":[0.2502177721],"iteration":725,"passed_time":4.165710561,"remaining_time":1.572182774},
{"learn":[0.24995262],"iteration":726,"passed_time":4.170622774,"remaining_time":1.566134824},
{"learn":[0.2496874134],"iteration":727,"passed_time":4.175865442,"remaining_time":1.560213462},
{"learn":[0.2494368899],"iteration":728,"passed_time":4.182288028,"remaining_time":1.554732586},
{"learn":[0.2491697812],"iteration":729,"passed_time":4.188079255,"remaining_time":1.549015615},
{"learn":[0.2489000723],"iteration":730,"passed_time":4.194802192,"remaining_time":1.543641299},
{"learn":[0.2487213481],"iteration":731,"passed_time":4.200993854,"remaining_time":1.538068788},
{"learn":[0.2484483647],"iteration":732,"passed_time":4.206803325,"remaining_time":1.532355372},
{"learn":[0.2482302418],"iteration":733,"passed_time":4.212850911,"remaining_time":1.526727987},
{"learn":[0.2478840798],"iteration":734,"passed_time":4.21858546,"remaining_time":1.520986594},
{"learn":[0.2476129354],"iteration":735,"passed_time":4.22417359,"remaining_time":1.515192701},
{"learn":[0.2474034281],"iteration":736,"passed_time":4.229738909,"remaining_time":1.509391225},
{"learn":[0.2471469855],"iteration":737,"passed_time":4.235013984,"remaining_time":1.503487349},
{"learn":[0.2469682358],"iteration":738,"passed_time":4.240684489,"remaining_time":1.497724833},
{"learn":[0.2467707461],"iteration":739,"passed_time":4.246776317,"remaining_time":1.492110598},
{"learn":[0.2464264022],"iteration":740,"passed_time":4.252564774,"remaining_time":1.486389037},
{"learn":[0.2459553252],"iteration":741,"passed_time":4.258007846,"remaining_time":1.480547202},
{"learn":[0.2456414986],"iteration":742,"passed_time":4.263341085,"remaining_time":1.47466845},
{"learn":[0.245437406],"iteration":743,"passed_time":4.26882283,"remaining_time":1.468842264},
{"learn":[0.245204391],"iteration":744,"passed_time":4.274460593,"remaining_time":1.463070404},
{"learn":[0.2449251782],"iteration":745,"passed_time":4.280470681,"remaining_time":1.457425674},
{"learn":[0.2445723902],"iteration":746,"passed_time":4.286485992,"remaining_time":1.451781735},
{"learn":[0.2443809945],"iteration":747,"passed_time":4.292237257,"remaining_time":1.446047846},
{"learn":[0.2441007153],"iteration":748,"passed_time":4.298049858,"remaining_time":1.440334465},
{"learn":[0.2439594882],"iteration":749,"passed_time":4.30406439,"remaining_time":1.43468813},
{"learn":[0.2436456461],"iteration":750,"passed_time":4.309487343,"remaining_time":1.428844671},
{"learn":[0.2434328497],"iteration":751,"passed_time":4.315143356,"remaining_time":1.423079192},
{"learn":[0.2432355163],"iteration":752,"passed_time":4.320981474,"remaining_time":1.417373737},
{"learn":[0.242986699],"iteration":753,"passed_time":4.326659735,"remaining_time":1.411615776},
{"learn":[0.2429024191],"iteration":754,"passed_time":4.332040769,"remaining_time":1.405761574},
{"learn":[0.2426938083],"iteration":755,"passed_time":4.337313736,"remaining_time":1.399873746},
{"learn":[0.2426102093],"iteration":756,"passed_time":4.342557357,"remaining_time":1.393978121},
{"learn":[0.2423337852],"iteration":757,"passed_time":4.348386975,"remaining_time":1.388271303},
{"learn":[0.2420389193],"iteration":758,"passed_time":4.354823788,"remaining_time":1.38275696},
{"learn":[0.2418587179],"iteration":759,"passed_time":4.360753362,"remaining_time":1.377080009},
{"learn":[0.2416567139],"iteration":760,"passed_time":4.366357028,"remaining_time":1.371300039},
{"learn":[0.2415395504],"iteration":761,"passed_time":4.371755582,"remaining_time":1.365456468},
{"learn":[0.2413232621],"iteration":762,"passed_time":4.377108801,"remaining_time":1.359599981},
{"learn":[0.2411597091],"iteration":763,"passed_time":4.382439679,"remaining_time":1.353737911},
{"learn":[0.2410763686],"iteration":764,"passed_time":4.387623363,"remaining_time":1.347832013},
{"learn":[0.2408720533],"iteration":765,"passed_time":4.392880599,"remaining_time":1.34195047},
{"learn":[0.2405953093],"iteration":766,"passed_time":4.398144161,"remaining_time":1.336072477},
{"learn":[0.240265821],"iteration":767,"passed_time":4.403443068,"remaining_time":1.33020676},
{"learn":[0.2400549931],"iteration":768,"passed_time":4.408834515,"remaining_time":1.324370316},
{"learn":[0.2397179483],"iteration":769,"passed_time":4.414799061,"remaining_time":1.318706213},
{"learn":[0.2395881552],"iteration":770,"passed_time":4.420696845,"remaining_time":1.313021501},
{"learn":[0.2392290337],"iteration":771,"passed_time":4.426173809,"remaining_time":1.307211954},
{"learn":[0.2390387854],"iteration":772,"passed_time":4.432502466,"remaining_time":1.301653376},
{"learn":[0.2387636321],"iteration":773,"passed_time":4.438322331,"remaining_time":1.295944246},
{"learn":[0.2386089765],"iteration":774,"passed_time":4.444277016,"remaining_time":1.290273972},
{"learn":[0.2383720832],"iteration":775,"passed_time":4.450694531,"remaining_time":1.284736566},
{"learn":[0.2381728148],"iteration":776,"passed_time":4.456287615,"remaining_time":1.278960281},
{"learn":[0.2378204819],"iteration":777,"passed_time":4.461683055,"remaining_time":1.27312807},
{"learn":[0.2373297297],"iteration":778,"passed_time":4.466948038,"remaining_time":1.26725997},
{"learn":[0.2370622241],"iteration":779,"passed_time":4.47259165,"remaining_time":1.261500209},
{"learn":[0.2367820037],"iteration":780,"passed_time":4.478398565,"remaining_time":1.255786537},
{"learn":[0.2366374435],"iteration":781,"passed_time":4.484068628,"remaining_time":1.250034477},
{"learn":[0.2362634694],"iteration":782,"passed_time":4.489568097,"remaining_time":1.244235347},
{"learn":[0.2360075914],"iteration":783,"passed_time":4.494833289,"remaining_time":1.238372437},
{"learn":[0.235823669],"iteration":784,"passed_time":4.500171803,"remaining_time":1.232531131},
{"learn":[0.2355429116],"iteration":785,"passed_time":4.505505876,"remaining_time":1.226689895},
{"learn":[0.2352765322],"iteration":786,"passed_time":4.510891814,"remaining_time":1.220863985},
{"learn":[0.2350579306],"iteration":787,"passed_time":4.516303839,"remaining_time":1.21504621},
{"learn":[0.2348990971],"iteration":788,"passed_time":4.522783598,"remaining_time":1.209515005},
{"learn":[0.2346964543],"iteration":789,"passed_time":4.529090391,"remaining_time":1.20393542},
{"learn":[0.2344263778],"iteration":790,"passed_time":4.535231099,"remaining_time":1.198310113},
{"learn":[0.2343034121],"iteration":791,"passed_time":4.540860299,"remaining_time":1.192549169},
{"learn":[0.2341265626],"iteration":792,"passed_time":4.546591984,"remaining_time":1.18681531},
{"learn":[0.2338814235],"iteration":793,"passed_time":4.552684299,"remaining_time":1.18117502},
{"learn":[0.2337058224],"iteration":794,"passed_time":4.55896408,"remaining_time":1.175581932},
{"learn":[0.2335450772],"iteration":795,"passed_time":4.564665059,"remaining_time":1.169838784},
{"learn":[0.2332351156],"iteration":796,"passed_time":4.570385837,"remaining_time":1.164100784},
{"learn":[0.2329306918],"iteration":797,"passed_time":4.575770919,"remaining_time":1.158277852},
{"learn":[0.2326920976],"iteration":798,"passed_time":4.581338893,"remaining_time":1.152502025},
{"learn":[0.2324798111],"iteration":799,"passed_time":4.58643442,"remaining_time":1.146608605},
{"learn":[0.2321238371],"iteration":800,"passed_time":4.591980185,"remaining_time":1.140829035},
{"learn":[0.2318612707],"iteration":801,"passed_time":4.597076827,"remaining_time":1.134939167},
{"learn":[0.2316810434],"iteration":802,"passed_time":4.602110738,"remaining_time":1.129035885},
{"learn":[0.2315643672],"iteration":803,"passed_time":4.606947628,"remaining_time":1.123086735},
{"learn":[0.2314925924],"iteration":804,"passed_time":4.611981459,"remaining_time":1.117188055},
{"learn":[0.2312071062],"iteration":805,"passed_time":4.617232956,"remaining_time":1.111343913},
{"learn":[0.230960522],"iteration":806,"passed_time":4.622451461,"remaining_time":1.105493348},
{"learn":[0.2307225292],"iteration":807,"passed_time":4.627855903,"remaining_time":1.099688531},
{"learn":[0.2305524145],"iteration":808,"passed_time":4.632904007,"remaining_time":1.093800575},
{"learn":[0.2303450407],"iteration":809,"passed_time":4.637888196,"remaining_time":1.0878997},
{"learn":[0.2302385476],"iteration":810,"passed_time":4.644288432,"remaining_time":1.08233109},
{"learn":[0.2299758439],"iteration":811,"passed_time":4.650015084,"remaining_time":1.076604477},
{"learn":[0.2297052403],"iteration":812,"passed_time":4.656396776,"remaining_time":1.071028533},
{"learn":[0.2294624155],"iteration":813,"passed_time":4.662658424,"remaining_time":1.065423178},
{"learn":[0.2293826107],"iteration":814,"passed_time":4.667849696,"remaining_time":1.059573244},
{"learn":[0.2290823786],"iteration":815,"passed_time":4.673295133,"remaining_time":1.053782236},
{"learn":[0.228827579],"iteration":816,"passed_time":4.679393119,"remaining_time":1.048138238},
{"learn":[0.2286674494],"iteration":817,"passed_time":4.68492281,"remaining_time":1.042366689},
{"learn":[0.2285056409],"iteration":818,"passed_time":4.690471359,"remaining_time":1.036599897},
{"learn":[0.2283296194],"iteration":819,"passed_time":4.695515399,"remaining_time":1.030722892},
{"learn":[0.2280126284],"iteration":820,"passed_time":4.700429293,"remaining_time":1.024819541},
{"learn":[0.2278114704],"iteration":821,"passed_time":4.705541446,"remaining_time":1.01896153},
{"learn":[0.2276095905],"iteration":822,"passed_time":4.710905465,"remaining_time":1.013159499},
{"learn":[0.227320855],"iteration":823,"passed_time":4.71611736,"remaining_time":1.007326038},
{"learn":[0.2271659657],"iteration":824,"passed_time":4.721570781,"remaining_time":1.001545317},
{"learn":[0.2269228791],"iteration":825,"passed_time":4.72710309,"remaining_time":0.9957820068},
{"learn":[0.2267396067],"iteration":826,"passed_time":4.732767941,"remaining_time":0.9900469817},
{"learn":[0.2266933926],"iteration":827,"passed_time":4.738248008,"remaining_time":0.9842737407},
{"learn":[0.2264804931],"iteration":828,"passed_time":4.743503238,"remaining_time":0.9784548296},
{"learn":[0.2261851929],"iteration":829,"passed_time":4.748902932,"remaining_time":0.9726668656},
{"learn":[0.2259927492],"iteration":830,"passed_time":4.754570192,"remaining_time":0.9669342508},
{"learn":[0.2256017862],"iteration":831,"passed_time":4.76032651,"remaining_time":0.9612197761},
{"learn":[0.2254158483],"iteration":832,"passed_time":4.766069216,"remaining_time":0.955502472},
{"learn":[0.225204895],"iteration":833,"passed_time":4.771336661,"remaining_time":0.9496905104},
{"learn":[0.2249965355],"iteration":834,"passed_time":4.777038514,"remaining_time":0.9439656943},
{"learn":[0.2248405467],"iteration":835,"passed_time":4.783399101,"remaining_time":0.9383701586},
{"learn":[0.2246023464],"iteration":836,"passed_time":4.789466951,"remaining_time":0.9327157861},
{"learn":[0.2243473011],"iteration":837,"passed_time":4.795792137,"remaining_time":0.9271101745},
{"learn":[0.2240949857],"iteration":838,"passed_time":4.801669828,"remaining_time":0.9214169753},
{"learn":[0.2239632735],"iteration":839,"passed_time":4.807037219,"remaining_time":0.915626137},
{"learn":[0.2238578395],"iteration":840,"passed_time":4.812589856,"remaining_time":0.9098713283},
{"learn":[0.2236095008],"iteration":841,"passed_time":4.81797247,"remaining_time":0.9040850953},
{"learn":[0.2234404867],"iteration":842,"passed_time":4.823308153,"remaining_time":0.8982910795},
{"learn":[0.2233070761],"iteration":843,"passed_time":4.828604486,"remaining_time":0.8924908766},
{"learn":[0.2231128421],"iteration":844,"passed_time":4.833962594,"remaining_time":0.8867031976},
{"learn":[0.2228992844],"iteration":845,"passed_time":4.839266016,"remaining_time":0.8809065797},
{"learn":[0.2227614254],"iteration":846,"passed_time":4.845090215,"remaining_time":0.8752051983},
{"learn":[0.2226027685],"iteration":847,"passed_time":4.851600688,"remaining_time":0.8696265384},
{"learn":[0.2224300074],"iteration":848,"passed_time":4.858135538,"remaining_time":0.8640500191},
{"learn":[0.2222679698],"iteration":849,"passed_time":4.86404827,"remaining_time":0.8583614593},
{"learn":[0.2221005383],"iteration":850,"passed_time":4.870078387,"remaining_time":0.8526929256},
{"learn":[0.2219306777],"iteration":851,"passed_time":4.875909008,"remaining_time":0.8469888887},
{"learn":[0.2215831293],"iteration":852,"passed_time":4.88159713,"remaining_time":0.8412599978},
{"learn":[0.221287971],"iteration":853,"passed_time":4.887501739,"remaining_time":0.8355682129},
{"learn":[0.221063196],"iteration":854,"passed_time":4.89406021,"remaining_time":0.8299868193},
{"learn":[0.2207535126],"iteration":855,"passed_time":4.900371156,"remaining_time":0.8243615028},
{"learn":[0.220517162],"iteration":856,"passed_time":4.906351439,"remaining_time":0.8186794116},
{"learn":[0.2203710614],"iteration":857,"passed_time":4.912314031,"remaining_time":0.8129936975},
{"learn":[0.2202025482],"iteration":858,"passed_time":4.918292311,"remaining_time":0.8073099136},
{"learn":[0.220087937],"iteration":859,"passed_time":4.924366694,"remaining_time":0.8016410898},
{"learn":[0.2199948759],"iteration":860,"passed_time":4.930539968,"remaining_time":0.7959872888},
{"learn":[0.2196973429],"iteration":861,"passed_time":4.93669515,"remaining_time":0.790329386},
{"learn":[0.219521385],"iteration":862,"passed_time":4.943264092,"remaining_time":0.7847360145},
{"learn":[0.219316145],"iteration":863,"passed_time":4.949562763,"remaining_time":0.7790978423},
{"learn":[0.2190282324],"iteration":864,"passed_time":4.956073993,"remaining_time":0.7734913168},
{"learn":[0.2188507291],"iteration":865,"passed_time":4.962571289,"remaining_time":0.7678805459},
{"learn":[0.2186868037],"iteration":866,"passed_time":4.969108743,"remaining_time":0.7622738902},
{"learn":[0.2186111918],"iteration":867,"passed_time":4.975529954,"remaining_time":0.7566474124},
{"learn":[0.2183595856],"iteration":868,"passed_time":4.982065545,"remaining_time":0.751036348},
{"learn":[0.2181419235],"iteration":869,"passed_time":4.988299508,"remaining_time":0.7453780875},
{"learn":[0.2179368493],"iteration":870,"passed_time":4.994342229,"remaining_time":0.7396901809},
{"learn":[0.2177448791],"iteration":871,"passed_time":5.000614098,"remaining_time":0.734035097},
{"learn":[0.2174673822],"iteration":872,"passed_time":5.00666049,"remaining_time":0.7283457987},
{"learn":[0.2171925726],"iteration":873,"passed_time":5.012721656,"remaining_time":0.7226578131},
{"learn":[0.2170115683],"iteration":874,"passed_time":5.018350091,"remaining_time":0.7169071559},
{"learn":[0.2168297412],"iteration":875,"passed_time":5.024244101,"remaining_time":0.7111943704},
{"learn":[0.2166605949],"iteration":876,"passed_time":5.032717954,"remaining_time":0.705842997},
{"learn":[0.2165234433],"iteration":877,"passed_time":5.040108969,"remaining_time":0.7003340481},
{"learn":[0.2163446042],"iteration":878,"passed_time":5.047153138,"remaining_time":0.6947730713},
{"learn":[0.2162511907],"iteration":879,"passed_time":5.052328531,"remaining_time":0.6889538905},
{"learn":[0.2160260019],"iteration":880,"passed_time":5.057907065,"remaining_time":0.6831906251},
{"learn":[0.2159191486],"iteration":881,"passed_time":5.063837474,"remaining_time":0.6774748548},
{"learn":[0.2156583975],"iteration":882,"passed_time":5.069608315,"remaining_time":0.6717374551},
{"learn":[0.2155096214],"iteration":883,"passed_time":5.075304929,"remaining_time":0.6659902395},
{"learn":[0.2152375772],"iteration":884,"passed_time":5.081051586,"remaining_time":0.6602496411},
{"learn":[0.2150945962],"iteration":885,"passed_time":5.086604583,"remaining_time":0.6544841111},
{"learn":[0.2149426847],"iteration":886,"passed_time":5.092715213,"remaining_time":0.6487901004},
{"learn":[0.2147358454],"iteration":887,"passed_time":5.099338809,"remaining_time":0.6431598497},
{"learn":[0.214610881],"iteration":888,"passed_time":5.105748959,"remaining_time":0.6375007136},
{"learn":[0.2144437232],"iteration":889,"passed_time":5.111801699,"remaining_time":0.6317957157},
{"learn":[0.2142693045],"iteration":890,"passed_time":5.117227544,"remaining_time":0.6260132461},
{"learn":[0.2140434411],"iteration":891,"passed_time":5.123051301,"remaining_time":0.6202797539},
{"learn":[0.2138701821],"iteration":892,"passed_time":5.12905669,"remaining_time":0.6145678229},
{"learn":[0.2136132485],"iteration":893,"passed_time":5.135132776,"remaining_time":0.6088636177},
{"learn":[0.2134624918],"iteration":894,"passed_time":5.140844436,"remaining_time":0.6031158277},
{"learn":[0.2133689513],"iteration":895,"passed_time":5.1464887,"remaining_time":0.5973602955},
{"learn":[0.2132454272],"iteration":896,"passed_time":5.152353657,"remaining_time":0.5916303531},
{"learn":[0.2130210878],"iteration":897,"passed_time":5.1582486,"remaining_time":0.5859035158},
{"learn":[0.2128471208],"iteration":898,"passed_time":5.16404478,"remaining_time":0.5801652089},
{"learn":[0.2127172965],"iteration":899,"passed_time":5.169666545,"remaining_time":0.5744073939},
{"learn":[0.212527106],"iteration":900,"passed_time":5.175581081,"remaining_time":0.56868205},
{"learn":[0.2122008462],"iteration":901,"passed_time":5.181270061,"remaining_time":0.5629317804},
{"learn":[0.2119741792],"iteration":902,"passed_time":5.186959023,"remaining_time":0.5571816448},
{"learn":[0.2117535987],"iteration":903,"passed_time":5.192526775,"remaining_time":0.5514187726},
{"learn":[0.2115816774],"iteration":904,"passed_time":5.198158546,"remaining_time":0.5456630518},
{"learn":[0.2114509598],"iteration":905,"passed_time":5.20370636,"remaining_time":0.5398988939},
{"learn":[0.2113182271],"iteration":906,"passed_time":5.209304293,"remaining_time":0.534140352},
{"learn":[0.2110409238],"iteration":907,"passed_time":5.215217236,"remaining_time":0.5284140812},
{"learn":[0.2110115225],"iteration":908,"passed_time":5.220647984,"remaining_time":0.5226391272},
{"learn":[0.2106000172],"iteration":909,"passed_time":5.226602105,"remaining_time":0.5169166917},
{"learn":[0.210395882],"iteration":910,"passed_time":5.232112806,"remaining_time":0.5111504278},
{"learn":[0.2102973886],"iteration":911,"passed_time":5.237726737,"remaining_time":0.5053946852},
{"learn":[0.2100730723],"iteration":912,"passed_time":5.243733199,"remaining_time":0.4996766575},
{"learn":[0.2099354436],"iteration":913,"passed_time":5.250132061,"remaining_time":0.4939949204},
{"learn":[0.209700776],"iteration":914,"passed_time":5.25604587,"remaining_time":0.4882665563},
{"learn":[0.2095038327],"iteration":915,"passed_time":5.261691369,"remaining_time":0.4825131823},
{"learn":[0.2093204754],"iteration":916,"passed_time":5.267162174,"remaining_time":0.4767442317},
{"learn":[0.2091596606],"iteration":917,"passed_time":5.272898793,"remaining_time":0.4709996743},
{"learn":[0.2090656251],"iteration":918,"passed_time":5.2789559,"remaining_time":0.4652833818},
{"learn":[0.2088934061],"iteration":919,"passed_time":5.284984585,"remaining_time":0.459563877},
{"learn":[0.208651127],"iteration":920,"passed_time":5.290657384,"remaining_time":0.4538131741},
{"learn":[0.2083483632],"iteration":921,"passed_time":5.296180708,"remaining_time":0.4480499948},
{"learn":[0.208200321],"iteration":922,"passed_time":5.301577807,"remaining_time":0.4422768052},
{"learn":[0.2079944052],"iteration":923,"passed_time":5.307342243,"remaining_time":0.4365346434},
{"learn":[0.2077772751],"iteration":924,"passed_time":5.313333052,"remaining_time":0.430810788},
{"learn":[0.2076090892],"iteration":925,"passed_time":5.319573771,"remaining_time":0.4251063273},
{"learn":[0.2074481275],"iteration":926,"passed_time":5.326143418,"remaining_time":0.4194266122},
{"learn":[0.2073018394],"iteration":927,"passed_time":5.332156827,"remaining_time":0.4137018228},
{"learn":[0.2071530726],"iteration":928,"passed_time":5.338074366,"remaining_time":0.407969085},
{"learn":[0.2068143859],"iteration":929,"passed_time":5.34362182,"remaining_time":0.402208094},
{"learn":[0.2065408621],"iteration":930,"passed_time":5.349328268,"remaining_time":0.3964593453},
{"learn":[0.2064514139],"iteration":931,"passed_time":5.355127213,"remaining_time":0.3907174362},
{"learn":[0.2063068513],"iteration":932,"passed_time":5.361080423,"remaining_time":0.3849864827},
{"learn":[0.2061659093],"iteration":933,"passed_time":5.367403971,"remaining_time":0.3792812228},
{"learn":[0.2059497271],"iteration":934,"passed_time":5.373350698,"remaining_time":0.3735484442},
{"learn":[0.2059106109],"iteration":935,"passed_time":5.379055786,"remaining_time":0.3677986862},
{"learn":[0.2057236619],"iteration":936,"passed_time":5.384766165,"remaining_time":0.3620493793},
{"learn":[0.2055004061],"iteration":937,"passed_time":5.390702458,"remaining_time":0.3563150878},
{"learn":[0.2053254849],"iteration":938,"passed_time":5.396401098,"remaining_time":0.3505649276},
{"learn":[0.205137728],"iteration":939,"passed_time":5.402592006,"remaining_time":0.3448462983},
{"learn":[0.2049628965],"iteration":940,"passed_time":5.408865309,"remaining_time":0.3391318313},
{"learn":[0.2047858175],"iteration":941,"passed_time":5.414878344,"remaining_time":0.3334001528},
{"learn":[0.2045540516],"iteration":942,"passed_time":5.421211812,"remaining_time":0.3276872463},
{"learn":[0.2044176755],"iteration":943,"passed_time":5.427180715,"remaining_time":0.3219513984},
{"learn":[0.2042187617],"iteration":944,"passed_time":5.433130479,"remaining_time":0.3162139432},
{"learn":[0.2039983521],"iteration":945,"passed_time":5.438960611,"remaining_time":0.3104692104},
{"learn":[0.2037912103],"iteration":946,"passed_time":5.445144078,"remaining_time":0.304744072},
{"learn":[0.2036025763],"iteration":947,"passed_time":5.451385634,"remaining_time":0.2990211529},
{"learn":[0.2035104927],"iteration":948,"passed_time":5.457178536,"remaining_time":0.2932730298},
{"learn":[0.2034014104],"iteration":949,"passed_time":5.462672733,"remaining_time":0.2875090912},
{"learn":[0.2032867123],"iteration":950,"passed_time":5.468252453,"remaining_time":0.2817501264},
{"learn":[0.2030836288],"iteration":951,"passed_time":5.474010452,"remaining_time":0.276000527},
{"learn":[0.2029638052],"iteration":952,"passed_time":5.479975111,"remaining_time":0.270261102},
{"learn":[0.2027926552],"iteration":953,"passed_time":5.485977908,"remaining_time":0.2645230438},
{"learn":[0.2026503926],"iteration":954,"passed_time":5.492209855,"remaining_time":0.2587952288},
{"learn":[0.2024808726],"iteration":955,"passed_time":5.498283538,"remaining_time":0.253059075},
{"learn":[0.2022605645],"iteration":956,"passed_time":5.50403152,"remaining_time":0.2473075813},
{"learn":[0.2021020063],"iteration":957,"passed_time":5.510232033,"remaining_time":0.2415759346},
{"learn":[0.2019753324],"iteration":958,"passed_time":5.516408454,"remaining_time":0.2358422801},
{"learn":[0.2017685278],"iteration":959,"passed_time":5.522561097,"remaining_time":0.2301067124},
{"learn":[0.2014652984],"iteration":960,"passed_time":5.528638783,"remaining_time":0.2243672347},
{"learn":[0.2012586777],"iteration":961,"passed_time":5.534668428,"remaining_time":0.2186251562},
{"learn":[0.200971896],"iteration":962,"passed_time":5.540708862,"remaining_time":0.212882895},
{"learn":[0.200719034],"iteration":963,"passed_time":5.546573077,"remaining_time":0.2071334344},
{"learn":[0.2005306844],"iteration":964,"passed_time":5.552489286,"remaining_time":0.2013856218},
{"learn":[0.2003656095],"iteration":965,"passed_time":5.558367524,"remaining_time":0.195636124},
{"learn":[0.2002038272],"iteration":966,"passed_time":5.564386365,"remaining_time":0.1898911583},
{"learn":[0.1999982918],"iteration":967,"passed_time":5.570408287,"remaining_time":0.1841457285},
{"learn":[0.1998336159],"iteration":968,"passed_time":5.576384428,"remaining_time":0.1783982634},
{"learn":[0.1996997359],"iteration":969,"passed_time":5.581975243,"remaining_time":0.1726384096},
{"learn":[0.1995390934],"iteration":970,"passed_time":5.587218594,"remaining_time":0.1668685265},
{"learn":[0.1993884102],"iteration":971,"passed_time":5.592659031,"remaining_time":0.1611054042},
{"learn":[0.1992397035],"iteration":972,"passed_time":5.599158832,"remaining_time":0.1553723417},
{"learn":[0.1990436323],"iteration":973,"passed_time":5.605534555,"remaining_time":0.1496343926},
{"learn":[0.1987529764],"iteration":974,"passed_time":5.611628829,"remaining_time":0.1438879187},
{"learn":[0.1986132785],"iteration":975,"passed_time":5.617439308,"remaining_time":0.1381337535},
{"learn":[0.1983683128],"iteration":976,"passed_time":5.623090985,"remaining_time":0.1323757345},
{"learn":[0.1981486924],"iteration":977,"passed_time":5.629073081,"remaining_time":0.1266253658},
{"learn":[0.1980066613],"iteration":978,"passed_time":5.635585135,"remaining_time":0.1208858915},
{"learn":[0.1977990819],"iteration":979,"passed_time":5.641779387,"remaining_time":0.1151383548},
{"learn":[0.1975281249],"iteration":980,"passed_time":5.647562851,"remaining_time":0.1093819512},
{"learn":[0.1973237276],"iteration":981,"passed_time":5.653183576,"remaining_time":0.1036225095},
{"learn":[0.1971558016],"iteration":982,"passed_time":5.658759651,"remaining_time":0.0978625779},
{"learn":[0.1968969223],"iteration":983,"passed_time":5.665034207,"remaining_time":0.09211437734},
{"learn":[0.1966830306],"iteration":984,"passed_time":5.670929172,"remaining_time":0.08635932749},
{"learn":[0.196510369],"iteration":985,"passed_time":5.676705711,"remaining_time":0.08060231233},
{"learn":[0.1962995936],"iteration":986,"passed_time":5.682766445,"remaining_time":0.07484900079},
{"learn":[0.1961952953],"iteration":987,"passed_time":5.688452061,"remaining_time":0.06909051086},
{"learn":[0.1960443336],"iteration":988,"passed_time":5.694352636,"remaining_time":0.06333455914},
{"learn":[0.1959493196],"iteration":989,"passed_time":5.700281414,"remaining_time":0.05757860014},
{"learn":[0.1956859658],"iteration":990,"passed_time":5.706477155,"remaining_time":0.05182471685},
{"learn":[0.1955537489],"iteration":991,"passed_time":5.712247587,"remaining_time":0.0460665128},
{"learn":[0.1954342025],"iteration":992,"passed_time":5.717769348,"remaining_time":0.04030653115},
{"learn":[0.1951768903],"iteration":993,"passed_time":5.724094308,"remaining_time":0.03455187711},
{"learn":[0.19508574],"iteration":994,"passed_time":5.730127426,"remaining_time":0.02879461018},
{"learn":[0.1948746547],"iteration":995,"passed_time":5.736643249,"remaining_time":0.02303872791},
{"learn":[0.1946349102],"iteration":996,"passed_time":5.742881803,"remaining_time":0.01728048687},
{"learn":[0.194498631],"iteration":997,"passed_time":5.748680723,"remaining_time":0.01152040225},
{"learn":[0.1943147093],"iteration":998,"passed_time":5.75472025,"remaining_time":0.005760480731},
{"learn":[0.1941889901],"iteration":999,"passed_time":5.761201778,"remaining_time":0}
]}